{
 "displayFieldName": "OUTAGE_ID",
 "fieldAliases": {
  "OUTAGE_ID": "OUTAGE_ID",
  "CURRENT_ETOR": "Estimated Restoration",
  "OUTAGE_START": "Start Time",
  "EST_CUSTOMERS": "Customers Affected",
  "OUTAGE_CAUSE": "Cause",
  "CREW_CURRENT_STATUS": "Status",
  "LAST_UPDATE": "Last Updated",
  "OUTAGE_START_TEXT": "OUTAGE_START_TEXT",
  "LAST_UPDATE_TEXT": "LAST_UPDATE_TEXT",
  "CURRENT_ETOR_TEXT": "CURRENT_ETOR_TEXT"
 },
 "geometryType": "esriGeometryPoint",
 "spatialReference": {
  "wkid": 102100,
  "latestWkid": 3857
 },
 "fields": [
  {
   "name": "OUTAGE_ID",
   "type": "esriFieldTypeString",
   "alias": "OUTAGE_ID",
   "length": 255
  },
  {
   "name": "CURRENT_ETOR",
   "type": "esriFieldTypeDate",
   "alias": "Estimated Restoration",
   "length": 8
  },
  {
   "name": "OUTAGE_START",
   "type": "esriFieldTypeDate",
   "alias": "Start Time",
   "length": 8
  },
  {
   "name": "EST_CUSTOMERS",
   "type": "esriFieldTypeInteger",
   "alias": "Customers Affected"
  },
  {
   "name": "OUTAGE_CAUSE",
   "type": "esriFieldTypeString",
   "alias": "Cause",
   "length": 255
  },
  {
   "name": "CREW_CURRENT_STATUS",
   "type": "esriFieldTypeString",
   "alias": "Status",
   "length": 255
  },
  {
   "name": "LAST_UPDATE",
   "type": "esriFieldTypeDate",
   "alias": "Last Updated",
   "length": 8
  },
  {
   "name": "OUTAGE_START_TEXT",
   "type": "esriFieldTypeString",
   "alias": "OUTAGE_START_TEXT",
   "length": 255
  },
  {
   "name": "LAST_UPDATE_TEXT",
   "type": "esriFieldTypeString",
   "alias": "LAST_UPDATE_TEXT",
   "length": 255
  },
  {
   "name": "CURRENT_ETOR_TEXT",
   "type": "esriFieldTypeString",
   "alias": "CURRENT_ETOR_TEXT",
   "length": 255
  }
 ],
 "features": [
  {
   "attributes": {
    "OUTAGE_ID": "100447",
    "CURRENT_ETOR": 1765067400000,
    "OUTAGE_START": 1765040153000,
    "EST_CUSTOMERS": 1,
    "OUTAGE_CAUSE": "PLNND SHUTDOWN",
    "CREW_CURRENT_STATUS": "Crew On Site",
    "LAST_UPDATE": 1765040525000,
    "OUTAGE_START_TEXT": "2025-12-06T16:55:53Z",
    "LAST_UPDATE_TEXT": "2025-12-06T17:02:05Z",
    "CURRENT_ETOR_TEXT": "2025-12-07T00:30:00Z"
   },
   "geometry": {
    "x": -13465989.4252,
    "y": 4735725.9707999974
   }
  },
  {
   "attributes": {
    "OUTAGE_ID": "100532",
    "CURRENT_ETOR": 1765089000000,
    "OUTAGE_START": 1765041127000,
    "EST_CUSTOMERS": 145,
    "OUTAGE_CAUSE": null,
    "CREW_CURRENT_STATUS": "Awaiting T-Man",
    "LAST_UPDATE": 1765067435000,
    "OUTAGE_START_TEXT": "2025-12-06T17:12:07Z",
    "LAST_UPDATE_TEXT": "2025-12-07T00:30:35Z",
    "CURRENT_ETOR_TEXT": "2025-12-07T06:30:00Z"
   },
   "geometry": {
    "x": -13578803.9869,
    "y": 4479720.6688999981
   }
  },
  {
   "attributes": {
    "OUTAGE_ID": "100630",
    "CURRENT_ETOR": 1765073700000,
    "OUTAGE_START": 1765055028000,
    "EST_CUSTOMERS": 1,
    "OUTAGE_CAUSE": null,
    "CREW_CURRENT_STATUS": "Awaiting T-Man",
    "LAST_UPDATE": 1765055033000,
    "OUTAGE_START_TEXT": "2025-12-06T21:03:48Z",
    "LAST_UPDATE_TEXT": "2025-12-06T21:03:53Z",
    "CURRENT_ETOR_TEXT": "2025-12-07T02:15:00Z"
   },
   "geometry": {
    "x": -13578604.950199999,
    "y": 4546041.1432000026
   }
  },
  {
   "attributes": {
    "OUTAGE_ID": "100665",
    "CURRENT_ETOR": 1765073700000,
    "OUTAGE_START": 1765059388000,
    "EST_CUSTOMERS": 1,
    "OUTAGE_CAUSE": null,
    "CREW_CURRENT_STATUS": "Awaiting T-Man",
    "LAST_UPDATE": 1765059393000,
    "OUTAGE_START_TEXT": "2025-12-06T22:16:28Z",
    "LAST_UPDATE_TEXT": "2025-12-06T22:16:33Z",
    "CURRENT_ETOR_TEXT": "2025-12-07T02:15:00Z"
   },
   "geometry": {
    "x": -13629523.759,
    "y": 4546379.2779000029
   }
  },
  {
   "attributes": {
    "OUTAGE_ID": "100704",
    "CURRENT_ETOR": 1765095300000,
    "OUTAGE_START": 1765061533000,
    "EST_CUSTOMERS": 1,
    "OUTAGE_CAUSE": null,
    "CREW_CURRENT_STATUS": "Awaiting T-Man",
    "LAST_UPDATE": 1765061538000,
    "OUTAGE_START_TEXT": "2025-12-06T22:52:13Z",
    "LAST_UPDATE_TEXT": "2025-12-06T22:52:18Z",
    "CURRENT_ETOR_TEXT": "2025-12-07T08:15:00Z"
   },
   "geometry": {
    "x": -13586443.8325,
    "y": 4477237.121299997
   }
  },
  {
   "attributes": {
    "OUTAGE_ID": "100742",
    "CURRENT_ETOR": 1765082700000,
    "OUTAGE_START": 1765066190000,
    "EST_CUSTOMERS": 1,
    "OUTAGE_CAUSE": null,
    "CREW_CURRENT_STATUS": "T-Man Enroute",
    "LAST_UPDATE": 1765066192000,
    "OUTAGE_START_TEXT": "2025-12-07T00:09:50Z",
    "LAST_UPDATE_TEXT": "2025-12-07T00:09:52Z",
    "CURRENT_ETOR_TEXT": "2025-12-07T04:45:00Z"
   },
   "geometry": {
    "x": -13543193.000799999,
    "y": 4994431.5791999996
   }
  },
  {
   "attributes": {
    "OUTAGE_ID": "100379",
    "CURRENT_ETOR": 1765051200000,
    "OUTAGE_START": 1765036922000,
    "EST_CUSTOMERS": 1,
    "OUTAGE_CAUSE": "PLNND SHUTDOWN",
    "CREW_CURRENT_STATUS": "Crew On Site",
    "LAST_UPDATE": 1765037132000,
    "OUTAGE_START_TEXT": "2025-12-06T16:02:02Z",
    "LAST_UPDATE_TEXT": "2025-12-06T16:05:32Z",
    "CURRENT_ETOR_TEXT": "2025-12-06T20:00:00Z"
   },
   "geometry": {
    "x": -13459072.7116,
    "y": 4678322.6806999967
   }
  },
  {
   "attributes": {
    "OUTAGE_ID": "100401",
    "CURRENT_ETOR": 1765076400000,
    "OUTAGE_START": 1765037905000,
    "EST_CUSTOMERS": 14,
    "OUTAGE_CAUSE": "PLNND SHUTDOWN",
    "CREW_CURRENT_STATUS": "Crew On Site",
    "LAST_UPDATE": 1765064488000,
    "OUTAGE_START_TEXT": "2025-12-06T16:18:25Z",
    "LAST_UPDATE_TEXT": "2025-12-06T23:41:28Z",
    "CURRENT_ETOR_TEXT": "2025-12-07T03:00:00Z"
   },
   "geometry": {
    "x": -13609964.6327,
    "y": 4582118.6393999979
   }
  },
  {
   "attributes": {
    "OUTAGE_ID": "100705",
    "CURRENT_ETOR": 1765081800000,
    "OUTAGE_START": 1765061766000,
    "EST_CUSTOMERS": 1,
    "OUTAGE_CAUSE": "PATROLLING",
    "CREW_CURRENT_STATUS": "T-Man On Site",
    "LAST_UPDATE": 1765064236000,
    "OUTAGE_START_TEXT": "2025-12-06T22:56:06Z",
    "LAST_UPDATE_TEXT": "2025-12-06T23:37:16Z",
    "CURRENT_ETOR_TEXT": "2025-12-07T04:30:00Z"
   },
   "geometry": {
    "x": -13429901.112399999,
    "y": 4664386.1569000036
   }
  },
  {
   "attributes": {
    "OUTAGE_ID": "100738",
    "CURRENT_ETOR": 1765078200000,
    "OUTAGE_START": 1765065244000,
    "EST_CUSTOMERS": 1,
    "OUTAGE_CAUSE": null,
    "CREW_CURRENT_STATUS": "T-Man Enroute",
    "LAST_UPDATE": 1765065247000,
    "OUTAGE_START_TEXT": "2025-12-06T23:54:04Z",
    "LAST_UPDATE_TEXT": "2025-12-06T23:54:07Z",
    "CURRENT_ETOR_TEXT": "2025-12-07T03:30:00Z"
   },
   "geometry": {
    "x": -13650566.1086,
    "y": 4714037.009300001
   }
  },
  {
   "attributes": {
    "OUTAGE_ID": "100748",
    "CURRENT_ETOR": null,
    "OUTAGE_START": 1765067694000,
    "EST_CUSTOMERS": 1,
    "OUTAGE_CAUSE": null,
    "CREW_CURRENT_STATUS": "T-Man Enroute",
    "LAST_UPDATE": 1765067698000,
    "OUTAGE_START_TEXT": "2025-12-07T00:34:54Z",
    "LAST_UPDATE_TEXT": "2025-12-07T00:34:58Z",
    "CURRENT_ETOR_TEXT": null
   },
   "geometry": {
    "x": -13583826.2928,
    "y": 4572031.5209000036
   }
  },
  {
   "attributes": {
    "OUTAGE_ID": "100540",
    "CURRENT_ETOR": 1765073700000,
    "OUTAGE_START": 1765045405000,
    "EST_CUSTOMERS": 1,
    "OUTAGE_CAUSE": "PATROLLING",
    "CREW_CURRENT_STATUS": "Awaiting T-Man",
    "LAST_UPDATE": 1765067008000,
    "OUTAGE_START_TEXT": "2025-12-06T18:23:25Z",
    "LAST_UPDATE_TEXT": "2025-12-07T00:23:28Z",
    "CURRENT_ETOR_TEXT": "2025-12-07T02:15:00Z"
   },
   "geometry": {
    "x": -13587240.2083,
    "y": 4511543.5543000028
   }
  },
  {
   "attributes": {
    "OUTAGE_ID": "100709",
    "CURRENT_ETOR": 1765076400000,
    "OUTAGE_START": 1765062060000,
    "EST_CUSTOMERS": 8,
    "OUTAGE_CAUSE": "PLNND SHUTDOWN",
    "CREW_CURRENT_STATUS": "Crew On Site",
    "LAST_UPDATE": 1765062379000,
    "OUTAGE_START_TEXT": "2025-12-06T23:01:00Z",
    "LAST_UPDATE_TEXT": "2025-12-06T23:06:19Z",
    "CURRENT_ETOR_TEXT": "2025-12-07T03:00:00Z"
   },
   "geometry": {
    "x": -13547303.2788,
    "y": 4378361.3079999983
   }
  },
  {
   "attributes": {
    "OUTAGE_ID": "100710",
    "CURRENT_ETOR": 1765074600000,
    "OUTAGE_START": 1765062207000,
    "EST_CUSTOMERS": 1,
    "OUTAGE_CAUSE": "PATROLLING",
    "CREW_CURRENT_STATUS": "T-Man On Site",
    "LAST_UPDATE": 1765067302000,
    "OUTAGE_START_TEXT": "2025-12-06T23:03:27Z",
    "LAST_UPDATE_TEXT": "2025-12-07T00:28:22Z",
    "CURRENT_ETOR_TEXT": "2025-12-07T02:30:00Z"
   },
   "geometry": {
    "x": -13820415.9134,
    "y": 4977027.9654999971
   }
  },
  {
   "attributes": {
    "OUTAGE_ID": "100732",
    "CURRENT_ETOR": 1765078200000,
    "OUTAGE_START": 1765064036000,
    "EST_CUSTOMERS": 1,
    "OUTAGE_CAUSE": null,
    "CREW_CURRENT_STATUS": "Awaiting T-Man",
    "LAST_UPDATE": 1765064038000,
    "OUTAGE_START_TEXT": "2025-12-06T23:33:56Z",
    "LAST_UPDATE_TEXT": "2025-12-06T23:33:58Z",
    "CURRENT_ETOR_TEXT": "2025-12-07T03:30:00Z"
   },
   "geometry": {
    "x": -13620799.946699999,
    "y": 4572510.5183999985
   }
  },
  {
   "attributes": {
    "OUTAGE_ID": "100743",
    "CURRENT_ETOR": 1765095300000,
    "OUTAGE_START": 1765066313000,
    "EST_CUSTOMERS": 1,
    "OUTAGE_CAUSE": "PATROLLING",
    "CREW_CURRENT_STATUS": "T-Man On Site",
    "LAST_UPDATE": 1765067137000,
    "OUTAGE_START_TEXT": "2025-12-07T00:11:53Z",
    "LAST_UPDATE_TEXT": "2025-12-07T00:25:37Z",
    "CURRENT_ETOR_TEXT": "2025-12-07T08:15:00Z"
   },
   "geometry": {
    "x": -13569608.519400001,
    "y": 4384153.1451999992
   }
  },
  {
   "attributes": {
    "OUTAGE_ID": "99390",
    "CURRENT_ETOR": 1764979200000,
    "OUTAGE_START": 1764950429000,
    "EST_CUSTOMERS": 3,
    "OUTAGE_CAUSE": "PLNND SHUTDOWN",
    "CREW_CURRENT_STATUS": "Crew On Site",
    "LAST_UPDATE": 1764967954000,
    "OUTAGE_START_TEXT": "2025-12-05T16:00:29Z",
    "LAST_UPDATE_TEXT": "2025-12-05T20:52:34Z",
    "CURRENT_ETOR_TEXT": "2025-12-06T00:00:00Z"
   },
   "geometry": {
    "x": -13440614.57,
    "y": 4231042.6715999991
   }
  },
  {
   "attributes": {
    "OUTAGE_ID": "100293",
    "CURRENT_ETOR": 1765029600000,
    "OUTAGE_START": 1765018896000,
    "EST_CUSTOMERS": 13,
    "OUTAGE_CAUSE": "PLNND SHUTDOWN",
    "CREW_CURRENT_STATUS": "Awaiting Crew",
    "LAST_UPDATE": 1765034641000,
    "OUTAGE_START_TEXT": "2025-12-06T11:01:36Z",
    "LAST_UPDATE_TEXT": "2025-12-06T15:24:01Z",
    "CURRENT_ETOR_TEXT": "2025-12-06T14:00:00Z"
   },
   "geometry": {
    "x": -13254993.5912,
    "y": 4207146.1595999971
   }
  },
  {
   "attributes": {
    "OUTAGE_ID": "100403",
    "CURRENT_ETOR": 1765076400000,
    "OUTAGE_START": 1765037946000,
    "EST_CUSTOMERS": 26,
    "OUTAGE_CAUSE": "PLNND SHUTDOWN",
    "CREW_CURRENT_STATUS": "Crew On Site",
    "LAST_UPDATE": 1765063502000,
    "OUTAGE_START_TEXT": "2025-12-06T16:19:06Z",
    "LAST_UPDATE_TEXT": "2025-12-06T23:25:02Z",
    "CURRENT_ETOR_TEXT": "2025-12-07T03:00:00Z"
   },
   "geometry": {
    "x": -13609964.1109,
    "y": 4582238.1275999993
   }
  },
  {
   "attributes": {
    "OUTAGE_ID": "100489",
    "CURRENT_ETOR": 1765072800000,
    "OUTAGE_START": 1765043429000,
    "EST_CUSTOMERS": 1,
    "OUTAGE_CAUSE": null,
    "CREW_CURRENT_STATUS": "Awaiting T-Man",
    "LAST_UPDATE": 1765065032000,
    "OUTAGE_START_TEXT": "2025-12-06T17:50:29Z",
    "LAST_UPDATE_TEXT": "2025-12-06T23:50:32Z",
    "CURRENT_ETOR_TEXT": "2025-12-07T02:00:00Z"
   },
   "geometry": {
    "x": -13538094.637499999,
    "y": 4395691.1347000003
   }
  },
  {
   "attributes": {
    "OUTAGE_ID": "100574",
    "CURRENT_ETOR": 1765051200000,
    "OUTAGE_START": 1765049263000,
    "EST_CUSTOMERS": 1,
    "OUTAGE_CAUSE": "PLNND SHUTDOWN",
    "CREW_CURRENT_STATUS": "Awaiting T-Man",
    "LAST_UPDATE": 1765049406000,
    "OUTAGE_START_TEXT": "2025-12-06T19:27:43Z",
    "LAST_UPDATE_TEXT": "2025-12-06T19:30:06Z",
    "CURRENT_ETOR_TEXT": "2025-12-06T20:00:00Z"
   },
   "geometry": {
    "x": -13472243.5623,
    "y": 4732351.8420000002
   }
  },
  {
   "attributes": {
    "OUTAGE_ID": "100583",
    "CURRENT_ETOR": 1765086300000,
    "OUTAGE_START": 1765051046000,
    "EST_CUSTOMERS": 9,
    "OUTAGE_CAUSE": "NG CONNECTION",
    "CREW_CURRENT_STATUS": "Awaiting Crew",
    "LAST_UPDATE": 1765052873000,
    "OUTAGE_START_TEXT": "2025-12-06T19:57:26Z",
    "LAST_UPDATE_TEXT": "2025-12-06T20:27:53Z",
    "CURRENT_ETOR_TEXT": "2025-12-07T05:45:00Z"
   },
   "geometry": {
    "x": -13624101.8167,
    "y": 4540843.9880999997
   }
  },
  {
   "attributes": {
    "OUTAGE_ID": "100648",
    "CURRENT_ETOR": 1765078200000,
    "OUTAGE_START": 1765056708000,
    "EST_CUSTOMERS": 3,
    "OUTAGE_CAUSE": "EMERG REPAIRS",
    "CREW_CURRENT_STATUS": "Awaiting Crew",
    "LAST_UPDATE": 1765065096000,
    "OUTAGE_START_TEXT": "2025-12-06T21:31:48Z",
    "LAST_UPDATE_TEXT": "2025-12-06T23:51:36Z",
    "CURRENT_ETOR_TEXT": "2025-12-07T03:30:00Z"
   },
   "geometry": {
    "x": -13586973.885,
    "y": 4527079.5979999974
   }
  },
  {
   "attributes": {
    "OUTAGE_ID": "100664",
    "CURRENT_ETOR": 1765081800000,
    "OUTAGE_START": 1765059331000,
    "EST_CUSTOMERS": 1,
    "OUTAGE_CAUSE": "PATROLLING",
    "CREW_CURRENT_STATUS": "T-Man On Site",
    "LAST_UPDATE": 1765066056000,
    "OUTAGE_START_TEXT": "2025-12-06T22:15:31Z",
    "LAST_UPDATE_TEXT": "2025-12-07T00:07:36Z",
    "CURRENT_ETOR_TEXT": "2025-12-07T04:30:00Z"
   },
   "geometry": {
    "x": -13501371.401799999,
    "y": 4553351.694600001
   }
  },
  {
   "attributes": {
    "OUTAGE_ID": "100730",
    "CURRENT_ETOR": 1765078200000,
    "OUTAGE_START": 1765063848000,
    "EST_CUSTOMERS": 3,
    "OUTAGE_CAUSE": "THRD PARTY",
    "CREW_CURRENT_STATUS": "Crew On Site",
    "LAST_UPDATE": 1765064312000,
    "OUTAGE_START_TEXT": "2025-12-06T23:30:48Z",
    "LAST_UPDATE_TEXT": "2025-12-06T23:38:32Z",
    "CURRENT_ETOR_TEXT": "2025-12-07T03:30:00Z"
   },
   "geometry": {
    "x": -13295261.634,
    "y": 4246913.2459999993
   }
  },
  {
   "attributes": {
    "OUTAGE_ID": "99406",
    "CURRENT_ETOR": 1764979200000,
    "OUTAGE_START": 1764950895000,
    "EST_CUSTOMERS": 4,
    "OUTAGE_CAUSE": "PLNND SHUTDOWN",
    "CREW_CURRENT_STATUS": "Awaiting T-Man",
    "LAST_UPDATE": 1764979790000,
    "OUTAGE_START_TEXT": "2025-12-05T16:08:15Z",
    "LAST_UPDATE_TEXT": "2025-12-06T00:09:50Z",
    "CURRENT_ETOR_TEXT": "2025-12-06T00:00:00Z"
   },
   "geometry": {
    "x": -13478781.776999999,
    "y": 4719088.4243000001
   }
  },
  {
   "attributes": {
    "OUTAGE_ID": "100634",
    "CURRENT_ETOR": 1765086300000,
    "OUTAGE_START": 1765055315000,
    "EST_CUSTOMERS": 1,
    "OUTAGE_CAUSE": "PATROLLING",
    "CREW_CURRENT_STATUS": "Awaiting T-Man",
    "LAST_UPDATE": 1765061431000,
    "OUTAGE_START_TEXT": "2025-12-06T21:08:35Z",
    "LAST_UPDATE_TEXT": "2025-12-06T22:50:31Z",
    "CURRENT_ETOR_TEXT": "2025-12-07T05:45:00Z"
   },
   "geometry": {
    "x": -13303396.931,
    "y": 4446092.2555999979
   }
  },
  {
   "attributes": {
    "OUTAGE_ID": "100729",
    "CURRENT_ETOR": 1765154100000,
    "OUTAGE_START": 1765038600000,
    "EST_CUSTOMERS": 11,
    "OUTAGE_CAUSE": "PLNND SHUTDOWN",
    "CREW_CURRENT_STATUS": "Awaiting T-Man",
    "LAST_UPDATE": 1765067705000,
    "OUTAGE_START_TEXT": "2025-12-06T16:30:00Z",
    "LAST_UPDATE_TEXT": "2025-12-07T00:35:05Z",
    "CURRENT_ETOR_TEXT": "2025-12-08T00:35:00Z"
   },
   "geometry": {
    "x": -13466295.546500001,
    "y": 4736020.5270000026
   }
  },
  {
   "attributes": {
    "OUTAGE_ID": "100745",
    "CURRENT_ETOR": null,
    "OUTAGE_START": 1765067156000,
    "EST_CUSTOMERS": 1,
    "OUTAGE_CAUSE": null,
    "CREW_CURRENT_STATUS": "Awaiting T-Man",
    "LAST_UPDATE": 1765067158000,
    "OUTAGE_START_TEXT": "2025-12-07T00:25:56Z",
    "LAST_UPDATE_TEXT": "2025-12-07T00:25:58Z",
    "CURRENT_ETOR_TEXT": null
   },
   "geometry": {
    "x": -13620194.197700001,
    "y": 4571491.5689999983
   }
  },
  {
   "attributes": {
    "OUTAGE_ID": "18973",
    "CURRENT_ETOR": 1765265400000,
    "OUTAGE_START": 1757353985000,
    "EST_CUSTOMERS": 5,
    "OUTAGE_CAUSE": "EMERG REPAIRS",
    "CREW_CURRENT_STATUS": "Awaiting T-Man",
    "LAST_UPDATE": 1762672711000,
    "OUTAGE_START_TEXT": "2025-09-08T17:53:05Z",
    "LAST_UPDATE_TEXT": "2025-11-09T07:18:31Z",
    "CURRENT_ETOR_TEXT": "2025-12-09T07:30:00Z"
   },
   "geometry": {
    "x": -13585653.5087,
    "y": 4604694.6525999978
   }
  },
  {
   "attributes": {
    "OUTAGE_ID": "97510",
    "CURRENT_ETOR": 1764801000000,
    "OUTAGE_START": 1764779716000,
    "EST_CUSTOMERS": 1,
    "OUTAGE_CAUSE": "PLNND SHUTDOWN",
    "CREW_CURRENT_STATUS": "Awaiting Crew",
    "LAST_UPDATE": 1764792698000,
    "OUTAGE_START_TEXT": "2025-12-03T16:35:16Z",
    "LAST_UPDATE_TEXT": "2025-12-03T20:11:38Z",
    "CURRENT_ETOR_TEXT": "2025-12-03T22:30:00Z"
   },
   "geometry": {
    "x": -13469150.7042,
    "y": 4756914.7395000011
   }
  },
  {
   "attributes": {
    "OUTAGE_ID": "100369",
    "CURRENT_ETOR": 1765071000000,
    "OUTAGE_START": 1765034580000,
    "EST_CUSTOMERS": 1,
    "OUTAGE_CAUSE": "PLNND SHUTDOWN",
    "CREW_CURRENT_STATUS": "Crew On Site",
    "LAST_UPDATE": 1765055730000,
    "OUTAGE_START_TEXT": "2025-12-06T15:23:00Z",
    "LAST_UPDATE_TEXT": "2025-12-06T21:15:30Z",
    "CURRENT_ETOR_TEXT": "2025-12-07T01:30:00Z"
   },
   "geometry": {
    "x": -13455084.814399999,
    "y": 4724695.9333999977
   }
  },
  {
   "attributes": {
    "OUTAGE_ID": "100417",
    "CURRENT_ETOR": 1765072800000,
    "OUTAGE_START": 1765038517000,
    "EST_CUSTOMERS": 1,
    "OUTAGE_CAUSE": "DAMGE UG CABLE",
    "CREW_CURRENT_STATUS": "Crew On Site",
    "LAST_UPDATE": 1765060122000,
    "OUTAGE_START_TEXT": "2025-12-06T16:28:37Z",
    "LAST_UPDATE_TEXT": "2025-12-06T22:28:42Z",
    "CURRENT_ETOR_TEXT": "2025-12-07T02:00:00Z"
   },
   "geometry": {
    "x": -13586443.8325,
    "y": 4477237.121299997
   }
  },
  {
   "attributes": {
    "OUTAGE_ID": "100562",
    "CURRENT_ETOR": 1765070100000,
    "OUTAGE_START": 1765048405000,
    "EST_CUSTOMERS": 1,
    "OUTAGE_CAUSE": "PATROLLING",
    "CREW_CURRENT_STATUS": "T-Man On Site",
    "LAST_UPDATE": 1765064381000,
    "OUTAGE_START_TEXT": "2025-12-06T19:13:25Z",
    "LAST_UPDATE_TEXT": "2025-12-06T23:39:41Z",
    "CURRENT_ETOR_TEXT": "2025-12-07T01:15:00Z"
   },
   "geometry": {
    "x": -13613983.834100001,
    "y": 4579470.5361000001
   }
  },
  {
   "attributes": {
    "OUTAGE_ID": "100564",
    "CURRENT_ETOR": 1765082700000,
    "OUTAGE_START": 1765048510000,
    "EST_CUSTOMERS": 1,
    "OUTAGE_CAUSE": "DAMGE UG CABLE",
    "CREW_CURRENT_STATUS": "Awaiting Crew",
    "LAST_UPDATE": 1765061136000,
    "OUTAGE_START_TEXT": "2025-12-06T19:15:10Z",
    "LAST_UPDATE_TEXT": "2025-12-06T22:45:36Z",
    "CURRENT_ETOR_TEXT": "2025-12-07T04:45:00Z"
   },
   "geometry": {
    "x": -13365559.297899999,
    "y": 4442664.8539000005
   }
  },
  {
   "attributes": {
    "OUTAGE_ID": "100632",
    "CURRENT_ETOR": 1765081800000,
    "OUTAGE_START": 1765055099000,
    "EST_CUSTOMERS": 1,
    "OUTAGE_CAUSE": null,
    "CREW_CURRENT_STATUS": "Awaiting T-Man",
    "LAST_UPDATE": 1765055232000,
    "OUTAGE_START_TEXT": "2025-12-06T21:04:59Z",
    "LAST_UPDATE_TEXT": "2025-12-06T21:07:12Z",
    "CURRENT_ETOR_TEXT": "2025-12-07T04:30:00Z"
   },
   "geometry": {
    "x": -13537751.5496,
    "y": 4394176.8276000023
   }
  },
  {
   "attributes": {
    "OUTAGE_ID": "100708",
    "CURRENT_ETOR": 1765074600000,
    "OUTAGE_START": 1765061903000,
    "EST_CUSTOMERS": 24,
    "OUTAGE_CAUSE": "EMERG REPAIRS",
    "CREW_CURRENT_STATUS": "Crew On Site",
    "LAST_UPDATE": 1765062362000,
    "OUTAGE_START_TEXT": "2025-12-06T22:58:23Z",
    "LAST_UPDATE_TEXT": "2025-12-06T23:06:02Z",
    "CURRENT_ETOR_TEXT": "2025-12-07T02:30:00Z"
   },
   "geometry": {
    "x": -13633818.930399999,
    "y": 4531504.4275000021
   }
  },
  {
   "attributes": {
    "OUTAGE_ID": "100734",
    "CURRENT_ETOR": 1765080900000,
    "OUTAGE_START": 1765064180000,
    "EST_CUSTOMERS": 1,
    "OUTAGE_CAUSE": "PATROLLING",
    "CREW_CURRENT_STATUS": "T-Man On Site",
    "LAST_UPDATE": 1765066007000,
    "OUTAGE_START_TEXT": "2025-12-06T23:36:20Z",
    "LAST_UPDATE_TEXT": "2025-12-07T00:06:47Z",
    "CURRENT_ETOR_TEXT": "2025-12-07T04:15:00Z"
   },
   "geometry": {
    "x": -13307180.6368,
    "y": 4398843.0914999992
   }
  },
  {
   "attributes": {
    "OUTAGE_ID": "100737",
    "CURRENT_ETOR": 1765078200000,
    "OUTAGE_START": 1765065152000,
    "EST_CUSTOMERS": 1,
    "OUTAGE_CAUSE": null,
    "CREW_CURRENT_STATUS": "Awaiting T-Man",
    "LAST_UPDATE": 1765065153000,
    "OUTAGE_START_TEXT": "2025-12-06T23:52:32Z",
    "LAST_UPDATE_TEXT": "2025-12-06T23:52:33Z",
    "CURRENT_ETOR_TEXT": "2025-12-07T03:30:00Z"
   },
   "geometry": {
    "x": -13631955.4553,
    "y": 4527725.0477000028
   }
  },
  {
   "attributes": {
    "OUTAGE_ID": "100746",
    "CURRENT_ETOR": null,
    "OUTAGE_START": 1765067420000,
    "EST_CUSTOMERS": 1,
    "OUTAGE_CAUSE": null,
    "CREW_CURRENT_STATUS": "Awaiting T-Man",
    "LAST_UPDATE": 1765067424000,
    "OUTAGE_START_TEXT": "2025-12-07T00:30:20Z",
    "LAST_UPDATE_TEXT": "2025-12-07T00:30:24Z",
    "CURRENT_ETOR_TEXT": null
   },
   "geometry": {
    "x": -13615128.4506,
    "y": 4563813.4526999965
   }
  },
  {
   "attributes": {
    "OUTAGE_ID": "100747",
    "CURRENT_ETOR": null,
    "OUTAGE_START": 1765067575000,
    "EST_CUSTOMERS": 1,
    "OUTAGE_CAUSE": null,
    "CREW_CURRENT_STATUS": "Awaiting T-Man",
    "LAST_UPDATE": 1765067578000,
    "OUTAGE_START_TEXT": "2025-12-07T00:32:55Z",
    "LAST_UPDATE_TEXT": "2025-12-07T00:32:58Z",
    "CURRENT_ETOR_TEXT": null
   },
   "geometry": {
    "x": -13584090.1899,
    "y": 4616673.8219999969
   }
  },
  {
   "attributes": {
    "OUTAGE_ID": "99685",
    "CURRENT_ETOR": 1765072800000,
    "OUTAGE_START": 1764952860000,
    "EST_CUSTOMERS": 19,
    "OUTAGE_CAUSE": "PLNND SHUTDOWN",
    "CREW_CURRENT_STATUS": "Crew On Site",
    "LAST_UPDATE": 1765066973000,
    "OUTAGE_START_TEXT": "2025-12-05T16:41:00Z",
    "LAST_UPDATE_TEXT": "2025-12-07T00:22:53Z",
    "CURRENT_ETOR_TEXT": "2025-12-07T02:00:00Z"
   },
   "geometry": {
    "x": -13569314.9629,
    "y": 4532550.8122000024
   }
  },
  {
   "attributes": {
    "OUTAGE_ID": "100395",
    "CURRENT_ETOR": 1765060200000,
    "OUTAGE_START": 1765037615000,
    "EST_CUSTOMERS": 2,
    "OUTAGE_CAUSE": null,
    "CREW_CURRENT_STATUS": "Awaiting T-Man",
    "LAST_UPDATE": 1765038285000,
    "OUTAGE_START_TEXT": "2025-12-06T16:13:35Z",
    "LAST_UPDATE_TEXT": "2025-12-06T16:24:45Z",
    "CURRENT_ETOR_TEXT": "2025-12-06T22:30:00Z"
   },
   "geometry": {
    "x": -13568946.091,
    "y": 4498456.0557999983
   }
  },
  {
   "attributes": {
    "OUTAGE_ID": "100419",
    "CURRENT_ETOR": 1765072800000,
    "OUTAGE_START": 1765038720000,
    "EST_CUSTOMERS": 57,
    "OUTAGE_CAUSE": "EMERG REPAIRS",
    "CREW_CURRENT_STATUS": "Crew On Site",
    "LAST_UPDATE": 1765055168000,
    "OUTAGE_START_TEXT": "2025-12-06T16:32:00Z",
    "LAST_UPDATE_TEXT": "2025-12-06T21:06:08Z",
    "CURRENT_ETOR_TEXT": "2025-12-07T02:00:00Z"
   },
   "geometry": {
    "x": -13398140.425999999,
    "y": 4450773.5966000035
   }
  },
  {
   "attributes": {
    "OUTAGE_ID": "100573",
    "CURRENT_ETOR": 1765051200000,
    "OUTAGE_START": 1765049319000,
    "EST_CUSTOMERS": 1,
    "OUTAGE_CAUSE": "PLNND SHUTDOWN",
    "CREW_CURRENT_STATUS": "Awaiting T-Man",
    "LAST_UPDATE": 1765049401000,
    "OUTAGE_START_TEXT": "2025-12-06T19:28:39Z",
    "LAST_UPDATE_TEXT": "2025-12-06T19:30:01Z",
    "CURRENT_ETOR_TEXT": "2025-12-06T20:00:00Z"
   },
   "geometry": {
    "x": -13472361.943399999,
    "y": 4732176.0557999983
   }
  },
  {
   "attributes": {
    "OUTAGE_ID": "100718",
    "CURRENT_ETOR": 1765078200000,
    "OUTAGE_START": 1765062960000,
    "EST_CUSTOMERS": 762,
    "OUTAGE_CAUSE": "PATROLLING",
    "CREW_CURRENT_STATUS": "T-Man On Site",
    "LAST_UPDATE": 1765066998000,
    "OUTAGE_START_TEXT": "2025-12-06T23:16:00Z",
    "LAST_UPDATE_TEXT": "2025-12-07T00:23:18Z",
    "CURRENT_ETOR_TEXT": "2025-12-07T03:30:00Z"
   },
   "geometry": {
    "x": -13428495.5967,
    "y": 4222877.9726999998
   }
  },
  {
   "attributes": {
    "OUTAGE_ID": "100726",
    "CURRENT_ETOR": 1765071900000,
    "OUTAGE_START": 1765056720000,
    "EST_CUSTOMERS": 13,
    "OUTAGE_CAUSE": null,
    "CREW_CURRENT_STATUS": "Awaiting T-Man",
    "LAST_UPDATE": 1765064102000,
    "OUTAGE_START_TEXT": "2025-12-06T21:32:00Z",
    "LAST_UPDATE_TEXT": "2025-12-06T23:35:02Z",
    "CURRENT_ETOR_TEXT": "2025-12-07T01:45:00Z"
   },
   "geometry": {
    "x": -13465635.57,
    "y": 4735966.9958999977
   }
  },
  {
   "attributes": {
    "OUTAGE_ID": "100731",
    "CURRENT_ETOR": 1765077300000,
    "OUTAGE_START": 1765064011000,
    "EST_CUSTOMERS": 1,
    "OUTAGE_CAUSE": null,
    "CREW_CURRENT_STATUS": "T-Man Enroute",
    "LAST_UPDATE": 1765064013000,
    "OUTAGE_START_TEXT": "2025-12-06T23:33:31Z",
    "LAST_UPDATE_TEXT": "2025-12-06T23:33:33Z",
    "CURRENT_ETOR_TEXT": "2025-12-07T03:15:00Z"
   },
   "geometry": {
    "x": -13387019.689100001,
    "y": 4450929.1491999999
   }
  },
  {
   "attributes": {
    "OUTAGE_ID": "100741",
    "CURRENT_ETOR": 1765084500000,
    "OUTAGE_START": 1765065873000,
    "EST_CUSTOMERS": 10,
    "OUTAGE_CAUSE": null,
    "CREW_CURRENT_STATUS": "Awaiting T-Man",
    "LAST_UPDATE": 1765065874000,
    "OUTAGE_START_TEXT": "2025-12-07T00:04:33Z",
    "LAST_UPDATE_TEXT": "2025-12-07T00:04:34Z",
    "CURRENT_ETOR_TEXT": "2025-12-07T05:15:00Z"
   },
   "geometry": {
    "x": -13392164.3039,
    "y": 4450094.4610000029
   }
  },
  {
   "attributes": {
    "OUTAGE_ID": "100744",
    "CURRENT_ETOR": 1765083600000,
    "OUTAGE_START": 1765066314000,
    "EST_CUSTOMERS": 1,
    "OUTAGE_CAUSE": "PATROLLING",
    "CREW_CURRENT_STATUS": "T-Man On Site",
    "LAST_UPDATE": 1765067385000,
    "OUTAGE_START_TEXT": "2025-12-07T00:11:54Z",
    "LAST_UPDATE_TEXT": "2025-12-07T00:29:45Z",
    "CURRENT_ETOR_TEXT": "2025-12-07T05:00:00Z"
   },
   "geometry": {
    "x": -13583788.1076,
    "y": 4516936.6458000019
   }
  },
  {
   "attributes": {
    "OUTAGE_ID": "100570",
    "CURRENT_ETOR": 1765071240000,
    "OUTAGE_START": 1765049070000,
    "EST_CUSTOMERS": 1,
    "OUTAGE_CAUSE": "EMERG REPAIRS",
    "CREW_CURRENT_STATUS": "Crew On Site",
    "LAST_UPDATE": 1765064059000,
    "OUTAGE_START_TEXT": "2025-12-06T19:24:30Z",
    "LAST_UPDATE_TEXT": "2025-12-06T23:34:19Z",
    "CURRENT_ETOR_TEXT": "2025-12-07T01:34:00Z"
   },
   "geometry": {
    "x": -13583940.590500001,
    "y": 4433156.7718999982
   }
  },
  {
   "attributes": {
    "OUTAGE_ID": "100655",
    "CURRENT_ETOR": 1765083600000,
    "OUTAGE_START": 1765058015000,
    "EST_CUSTOMERS": 1,
    "OUTAGE_CAUSE": null,
    "CREW_CURRENT_STATUS": "Awaiting T-Man",
    "LAST_UPDATE": 1765058017000,
    "OUTAGE_START_TEXT": "2025-12-06T21:53:35Z",
    "LAST_UPDATE_TEXT": "2025-12-06T21:53:37Z",
    "CURRENT_ETOR_TEXT": "2025-12-07T05:00:00Z"
   },
   "geometry": {
    "x": -13518546.490499999,
    "y": 4542134.6711999997
   }
  },
  {
   "attributes": {
    "OUTAGE_ID": "100657",
    "CURRENT_ETOR": 1765071900000,
    "OUTAGE_START": 1765058243000,
    "EST_CUSTOMERS": 1,
    "OUTAGE_CAUSE": "PATROLLING",
    "CREW_CURRENT_STATUS": "T-Man On Site",
    "LAST_UPDATE": 1765060325000,
    "OUTAGE_START_TEXT": "2025-12-06T21:57:23Z",
    "LAST_UPDATE_TEXT": "2025-12-06T22:32:05Z",
    "CURRENT_ETOR_TEXT": "2025-12-07T01:45:00Z"
   },
   "geometry": {
    "x": -13435004.410599999,
    "y": 4607535.0232999995
   }
  },
  {
   "attributes": {
    "OUTAGE_ID": "100659",
    "CURRENT_ETOR": 1765089000000,
    "OUTAGE_START": 1765058704000,
    "EST_CUSTOMERS": 1,
    "OUTAGE_CAUSE": null,
    "CREW_CURRENT_STATUS": "Awaiting T-Man",
    "LAST_UPDATE": 1765058708000,
    "OUTAGE_START_TEXT": "2025-12-06T22:05:04Z",
    "LAST_UPDATE_TEXT": "2025-12-06T22:05:08Z",
    "CURRENT_ETOR_TEXT": "2025-12-07T06:30:00Z"
   },
   "geometry": {
    "x": -13614080.765000001,
    "y": 4562041.1979999989
   }
  },
  {
   "attributes": {
    "OUTAGE_ID": "100700",
    "CURRENT_ETOR": 1765090800000,
    "OUTAGE_START": 1765061355000,
    "EST_CUSTOMERS": 1,
    "OUTAGE_CAUSE": "PATROLLING",
    "CREW_CURRENT_STATUS": "T-Man On Site",
    "LAST_UPDATE": 1765065698000,
    "OUTAGE_START_TEXT": "2025-12-06T22:49:15Z",
    "LAST_UPDATE_TEXT": "2025-12-07T00:01:38Z",
    "CURRENT_ETOR_TEXT": "2025-12-07T07:00:00Z"
   },
   "geometry": {
    "x": -13478766.1395,
    "y": 4238702.619599998
   }
  }
 ]
}