{
 "displayFieldName": "OUTAGE_ID",
 "fieldAliases": {
  "OUTAGE_ID": "OUTAGE_ID",
  "CURRENT_ETOR": "Estimated Restoration",
  "OUTAGE_START": "Start Time",
  "EST_CUSTOMERS": "Customers Affected",
  "OUTAGE_CAUSE": "Cause",
  "CREW_CURRENT_STATUS": "Status",
  "LAST_UPDATE": "Last Updated",
  "OUTAGE_START_TEXT": "OUTAGE_START_TEXT",
  "LAST_UPDATE_TEXT": "LAST_UPDATE_TEXT",
  "CURRENT_ETOR_TEXT": "CURRENT_ETOR_TEXT"
 },
 "geometryType": "esriGeometryPoint",
 "spatialReference": {
  "wkid": 102100,
  "latestWkid": 3857
 },
 "fields": [
  {
   "name": "OUTAGE_ID",
   "type": "esriFieldTypeString",
   "alias": "OUTAGE_ID",
   "length": 255
  },
  {
   "name": "CURRENT_ETOR",
   "type": "esriFieldTypeDate",
   "alias": "Estimated Restoration",
   "length": 8
  },
  {
   "name": "OUTAGE_START",
   "type": "esriFieldTypeDate",
   "alias": "Start Time",
   "length": 8
  },
  {
   "name": "EST_CUSTOMERS",
   "type": "esriFieldTypeInteger",
   "alias": "Customers Affected"
  },
  {
   "name": "OUTAGE_CAUSE",
   "type": "esriFieldTypeString",
   "alias": "Cause",
   "length": 255
  },
  {
   "name": "CREW_CURRENT_STATUS",
   "type": "esriFieldTypeString",
   "alias": "Status",
   "length": 255
  },
  {
   "name": "LAST_UPDATE",
   "type": "esriFieldTypeDate",
   "alias": "Last Updated",
   "length": 8
  },
  {
   "name": "OUTAGE_START_TEXT",
   "type": "esriFieldTypeString",
   "alias": "OUTAGE_START_TEXT",
   "length": 255
  },
  {
   "name": "LAST_UPDATE_TEXT",
   "type": "esriFieldTypeString",
   "alias": "LAST_UPDATE_TEXT",
   "length": 255
  },
  {
   "name": "CURRENT_ETOR_TEXT",
   "type": "esriFieldTypeString",
   "alias": "CURRENT_ETOR_TEXT",
   "length": 255
  }
 ],
 "features": [
  {
   "attributes": {
    "OUTAGE_ID": "229574",
    "CURRENT_ETOR": null,
    "OUTAGE_START": 1776786897000,
    "EST_CUSTOMERS": 1,
    "OUTAGE_CAUSE": "Awaiting Investigation",
    "CREW_CURRENT_STATUS": "No Access",
    "LAST_UPDATE": 1776800476000,
    "OUTAGE_START_TEXT": "2026-04-21T15:54:57Z",
    "LAST_UPDATE_TEXT": "2026-04-21T19:41:16Z",
    "CURRENT_ETOR_TEXT": null
   },
   "geometry": {
    "x": -13395941.7586,
    "y": 4148564.8650999963
   }
  },
  {
   "attributes": {
    "OUTAGE_ID": "229590",
    "CURRENT_ETOR": 1776812400000,
    "OUTAGE_START": 1776787133000,
    "EST_CUSTOMERS": 31,
    "OUTAGE_CAUSE": "PLNND SHUTDOWN",
    "CREW_CURRENT_STATUS": "Awaiting Crew",
    "LAST_UPDATE": 1776814463000,
    "OUTAGE_START_TEXT": "2026-04-21T15:58:53Z",
    "LAST_UPDATE_TEXT": "2026-04-21T23:34:23Z",
    "CURRENT_ETOR_TEXT": "2026-04-21T23:00:00Z"
   },
   "geometry": {
    "x": -13578178.202,
    "y": 4478414.1103999987
   }
  },
  {
   "attributes": {
    "OUTAGE_ID": "229794",
    "CURRENT_ETOR": 1776897000000,
    "OUTAGE_START": 1776797900000,
    "EST_CUSTOMERS": 2,
    "OUTAGE_CAUSE": "EMERG REPAIRS",
    "CREW_CURRENT_STATUS": "Awaiting Crew",
    "LAST_UPDATE": 1776829980000,
    "OUTAGE_START_TEXT": "2026-04-21T18:58:20Z",
    "LAST_UPDATE_TEXT": "2026-04-22T03:53:00Z",
    "CURRENT_ETOR_TEXT": "2026-04-22T22:30:00Z"
   },
   "geometry": {
    "x": -13495073.298799999,
    "y": 4594011.9215999991
   }
  },
  {
   "attributes": {
    "OUTAGE_ID": "229819",
    "CURRENT_ETOR": 1776897000000,
    "OUTAGE_START": 1776798840000,
    "EST_CUSTOMERS": 6,
    "OUTAGE_CAUSE": "REPLCE TXFMR",
    "CREW_CURRENT_STATUS": "Awaiting Crew",
    "LAST_UPDATE": 1776829980000,
    "OUTAGE_START_TEXT": "2026-04-21T19:14:00Z",
    "LAST_UPDATE_TEXT": "2026-04-22T03:53:00Z",
    "CURRENT_ETOR_TEXT": "2026-04-22T22:30:00Z"
   },
   "geometry": {
    "x": -13492706.8192,
    "y": 4594327.7106999978
   }
  },
  {
   "attributes": {
    "OUTAGE_ID": "229825",
    "CURRENT_ETOR": 1776897000000,
    "OUTAGE_START": 1776798952000,
    "EST_CUSTOMERS": 1,
    "OUTAGE_CAUSE": "Awaiting Investigation",
    "CREW_CURRENT_STATUS": "T-Man On Site",
    "LAST_UPDATE": 1776871828000,
    "OUTAGE_START_TEXT": "2026-04-21T19:15:52Z",
    "LAST_UPDATE_TEXT": "2026-04-22T15:30:28Z",
    "CURRENT_ETOR_TEXT": "2026-04-22T22:30:00Z"
   },
   "geometry": {
    "x": -13499119.477,
    "y": 4579098.248499997
   }
  },
  {
   "attributes": {
    "OUTAGE_ID": "229855",
    "CURRENT_ETOR": 1776886200000,
    "OUTAGE_START": 1776799904000,
    "EST_CUSTOMERS": 1,
    "OUTAGE_CAUSE": "THRD PARTY",
    "CREW_CURRENT_STATUS": "Crew On Site",
    "LAST_UPDATE": 1776813738000,
    "OUTAGE_START_TEXT": "2026-04-21T19:31:44Z",
    "LAST_UPDATE_TEXT": "2026-04-21T23:22:18Z",
    "CURRENT_ETOR_TEXT": "2026-04-22T19:30:00Z"
   },
   "geometry": {
    "x": -13596728.684500001,
    "y": 4608842.8640000001
   }
  },
  {
   "attributes": {
    "OUTAGE_ID": "229892",
    "CURRENT_ETOR": 1776897000000,
    "OUTAGE_START": 1776800925000,
    "EST_CUSTOMERS": 2,
    "OUTAGE_CAUSE": "REPLCE TXFMR",
    "CREW_CURRENT_STATUS": "Awaiting Crew",
    "LAST_UPDATE": 1776829980000,
    "OUTAGE_START_TEXT": "2026-04-21T19:48:45Z",
    "LAST_UPDATE_TEXT": "2026-04-22T03:53:00Z",
    "CURRENT_ETOR_TEXT": "2026-04-22T22:30:00Z"
   },
   "geometry": {
    "x": -13492298.879999999,
    "y": 4593517.635300003
   }
  },
  {
   "attributes": {
    "OUTAGE_ID": "229898",
    "CURRENT_ETOR": 1776891600000,
    "OUTAGE_START": 1776800940000,
    "EST_CUSTOMERS": 6,
    "OUTAGE_CAUSE": "PATROLLING",
    "CREW_CURRENT_STATUS": "T-Man Enroute",
    "LAST_UPDATE": 1776870644000,
    "OUTAGE_START_TEXT": "2026-04-21T19:49:00Z",
    "LAST_UPDATE_TEXT": "2026-04-22T15:10:44Z",
    "CURRENT_ETOR_TEXT": "2026-04-22T21:00:00Z"
   },
   "geometry": {
    "x": -13385877.109099999,
    "y": 4460042.9187999964
   }
  },
  {
   "attributes": {
    "OUTAGE_ID": "229942",
    "CURRENT_ETOR": 1776897000000,
    "OUTAGE_START": 1776802237000,
    "EST_CUSTOMERS": 15,
    "OUTAGE_CAUSE": "Awaiting Investigation",
    "CREW_CURRENT_STATUS": "T-Man On Site",
    "LAST_UPDATE": 1776871694000,
    "OUTAGE_START_TEXT": "2026-04-21T20:10:37Z",
    "LAST_UPDATE_TEXT": "2026-04-22T15:28:14Z",
    "CURRENT_ETOR_TEXT": "2026-04-22T22:30:00Z"
   },
   "geometry": {
    "x": -13476857.1756,
    "y": 4603299.6229000017
   }
  },
  {
   "attributes": {
    "OUTAGE_ID": "229952",
    "CURRENT_ETOR": 1776897000000,
    "OUTAGE_START": 1776802977000,
    "EST_CUSTOMERS": 2,
    "OUTAGE_CAUSE": "REPLCE TXFMR",
    "CREW_CURRENT_STATUS": "Awaiting Crew",
    "LAST_UPDATE": 1776834037000,
    "OUTAGE_START_TEXT": "2026-04-21T20:22:57Z",
    "LAST_UPDATE_TEXT": "2026-04-22T05:00:37Z",
    "CURRENT_ETOR_TEXT": "2026-04-22T22:30:00Z"
   },
   "geometry": {
    "x": -13471358.7633,
    "y": 4559978.6366999969
   }
  },
  {
   "attributes": {
    "OUTAGE_ID": "229957",
    "CURRENT_ETOR": 1776897000000,
    "OUTAGE_START": 1776802991000,
    "EST_CUSTOMERS": 1,
    "OUTAGE_CAUSE": "REPLCE TXFMR",
    "CREW_CURRENT_STATUS": "Awaiting Crew",
    "LAST_UPDATE": 1776863532000,
    "OUTAGE_START_TEXT": "2026-04-21T20:23:11Z",
    "LAST_UPDATE_TEXT": "2026-04-22T13:12:12Z",
    "CURRENT_ETOR_TEXT": "2026-04-22T22:30:00Z"
   },
   "geometry": {
    "x": -13472042.751800001,
    "y": 4558674.3550999984
   }
  },
  {
   "attributes": {
    "OUTAGE_ID": "229962",
    "CURRENT_ETOR": 1776897000000,
    "OUTAGE_START": 1776803159000,
    "EST_CUSTOMERS": 2,
    "OUTAGE_CAUSE": "BRKN POLE EQUIPMNT",
    "CREW_CURRENT_STATUS": "Awaiting Crew",
    "LAST_UPDATE": 1776871516000,
    "OUTAGE_START_TEXT": "2026-04-21T20:25:59Z",
    "LAST_UPDATE_TEXT": "2026-04-22T15:25:16Z",
    "CURRENT_ETOR_TEXT": "2026-04-22T22:30:00Z"
   },
   "geometry": {
    "x": -13470744.359299999,
    "y": 4560159.0024000034
   }
  },
  {
   "attributes": {
    "OUTAGE_ID": "229989",
    "CURRENT_ETOR": 1776897000000,
    "OUTAGE_START": 1776803816000,
    "EST_CUSTOMERS": 3,
    "OUTAGE_CAUSE": "REPLCE TXFMR",
    "CREW_CURRENT_STATUS": "Awaiting Crew",
    "LAST_UPDATE": 1776829980000,
    "OUTAGE_START_TEXT": "2026-04-21T20:36:56Z",
    "LAST_UPDATE_TEXT": "2026-04-22T03:53:00Z",
    "CURRENT_ETOR_TEXT": "2026-04-22T22:30:00Z"
   },
   "geometry": {
    "x": -13477930.5966,
    "y": 4547130.6687000021
   }
  },
  {
   "attributes": {
    "OUTAGE_ID": "229990",
    "CURRENT_ETOR": null,
    "OUTAGE_START": 1776803940000,
    "EST_CUSTOMERS": 2,
    "OUTAGE_CAUSE": "REPLCE TXFMR",
    "CREW_CURRENT_STATUS": "No Access",
    "LAST_UPDATE": 1776831209000,
    "OUTAGE_START_TEXT": "2026-04-21T20:39:00Z",
    "LAST_UPDATE_TEXT": "2026-04-22T04:13:29Z",
    "CURRENT_ETOR_TEXT": null
   },
   "geometry": {
    "x": -13378328.691599999,
    "y": 4441130.4918000028
   }
  },
  {
   "attributes": {
    "OUTAGE_ID": "229996",
    "CURRENT_ETOR": 1776897000000,
    "OUTAGE_START": 1776804360000,
    "EST_CUSTOMERS": 6,
    "OUTAGE_CAUSE": "NG CONNECTION",
    "CREW_CURRENT_STATUS": "Awaiting Crew",
    "LAST_UPDATE": 1776863616000,
    "OUTAGE_START_TEXT": "2026-04-21T20:46:00Z",
    "LAST_UPDATE_TEXT": "2026-04-22T13:13:36Z",
    "CURRENT_ETOR_TEXT": "2026-04-22T22:30:00Z"
   },
   "geometry": {
    "x": -13471198.717399999,
    "y": 4564861.3295999989
   }
  },
  {
   "attributes": {
    "OUTAGE_ID": "230016",
    "CURRENT_ETOR": 1776897000000,
    "OUTAGE_START": 1776803428000,
    "EST_CUSTOMERS": 5,
    "OUTAGE_CAUSE": "EMERG REPAIRS",
    "CREW_CURRENT_STATUS": "Awaiting Crew",
    "LAST_UPDATE": 1776835415000,
    "OUTAGE_START_TEXT": "2026-04-21T20:30:28Z",
    "LAST_UPDATE_TEXT": "2026-04-22T05:23:35Z",
    "CURRENT_ETOR_TEXT": "2026-04-22T22:30:00Z"
   },
   "geometry": {
    "x": -13473651.115,
    "y": 4585513.5405000001
   }
  },
  {
   "attributes": {
    "OUTAGE_ID": "230043",
    "CURRENT_ETOR": 1776888000000,
    "OUTAGE_START": 1776805800000,
    "EST_CUSTOMERS": 74,
    "OUTAGE_CAUSE": "BRKN UG EQUIPMNT",
    "CREW_CURRENT_STATUS": "Awaiting Crew",
    "LAST_UPDATE": 1776871456000,
    "OUTAGE_START_TEXT": "2026-04-21T21:10:00Z",
    "LAST_UPDATE_TEXT": "2026-04-22T15:24:16Z",
    "CURRENT_ETOR_TEXT": "2026-04-22T20:00:00Z"
   },
   "geometry": {
    "x": -13367485.739,
    "y": 4434107.4499000013
   }
  },
  {
   "attributes": {
    "OUTAGE_ID": "230046",
    "CURRENT_ETOR": 1776898020000,
    "OUTAGE_START": 1776805885000,
    "EST_CUSTOMERS": 1,
    "OUTAGE_CAUSE": "EMERG REPAIRS",
    "CREW_CURRENT_STATUS": "Awaiting Crew",
    "LAST_UPDATE": 1776833274000,
    "OUTAGE_START_TEXT": "2026-04-21T21:11:25Z",
    "LAST_UPDATE_TEXT": "2026-04-22T04:47:54Z",
    "CURRENT_ETOR_TEXT": "2026-04-22T22:47:00Z"
   },
   "geometry": {
    "x": -13390193.5776,
    "y": 4451171.1001000032
   }
  },
  {
   "attributes": {
    "OUTAGE_ID": "230075",
    "CURRENT_ETOR": 1776898800000,
    "OUTAGE_START": 1776807420000,
    "EST_CUSTOMERS": 8,
    "OUTAGE_CAUSE": "REPLCE TXFMR",
    "CREW_CURRENT_STATUS": "Awaiting Crew",
    "LAST_UPDATE": 1776824538000,
    "OUTAGE_START_TEXT": "2026-04-21T21:37:00Z",
    "LAST_UPDATE_TEXT": "2026-04-22T02:22:18Z",
    "CURRENT_ETOR_TEXT": "2026-04-22T23:00:00Z"
   },
   "geometry": {
    "x": -13477667.8893,
    "y": 4544107.5653000027
   }
  },
  {
   "attributes": {
    "OUTAGE_ID": "230077",
    "CURRENT_ETOR": 1776898800000,
    "OUTAGE_START": 1776807560000,
    "EST_CUSTOMERS": 3,
    "OUTAGE_CAUSE": "REPLCE TXFMR",
    "CREW_CURRENT_STATUS": "Awaiting Crew",
    "LAST_UPDATE": 1776830985000,
    "OUTAGE_START_TEXT": "2026-04-21T21:39:20Z",
    "LAST_UPDATE_TEXT": "2026-04-22T04:09:45Z",
    "CURRENT_ETOR_TEXT": "2026-04-22T23:00:00Z"
   },
   "geometry": {
    "x": -13478584.0792,
    "y": 4545604.2321999967
   }
  },
  {
   "attributes": {
    "OUTAGE_ID": "230079",
    "CURRENT_ETOR": 1776898800000,
    "OUTAGE_START": 1776807660000,
    "EST_CUSTOMERS": 4,
    "OUTAGE_CAUSE": "BRKN POLE EQUIPMNT",
    "CREW_CURRENT_STATUS": "Awaiting Crew",
    "LAST_UPDATE": 1776829115000,
    "OUTAGE_START_TEXT": "2026-04-21T21:41:00Z",
    "LAST_UPDATE_TEXT": "2026-04-22T03:38:35Z",
    "CURRENT_ETOR_TEXT": "2026-04-22T23:00:00Z"
   },
   "geometry": {
    "x": -13469870.171799999,
    "y": 4546104.7027999982
   }
  },
  {
   "attributes": {
    "OUTAGE_ID": "230084",
    "CURRENT_ETOR": 1776880800000,
    "OUTAGE_START": 1776807977000,
    "EST_CUSTOMERS": 1,
    "OUTAGE_CAUSE": "REPLCE TXFMR",
    "CREW_CURRENT_STATUS": "Awaiting Crew",
    "LAST_UPDATE": 1776829585000,
    "OUTAGE_START_TEXT": "2026-04-21T21:46:17Z",
    "LAST_UPDATE_TEXT": "2026-04-22T03:46:25Z",
    "CURRENT_ETOR_TEXT": "2026-04-22T18:00:00Z"
   },
   "geometry": {
    "x": -13477652.995200001,
    "y": 4545315.3222000003
   }
  },
  {
   "attributes": {
    "OUTAGE_ID": "230091",
    "CURRENT_ETOR": 1776897000000,
    "OUTAGE_START": 1776807994000,
    "EST_CUSTOMERS": 4,
    "OUTAGE_CAUSE": "STORM",
    "CREW_CURRENT_STATUS": "No Access",
    "LAST_UPDATE": 1776854507000,
    "OUTAGE_START_TEXT": "2026-04-21T21:46:34Z",
    "LAST_UPDATE_TEXT": "2026-04-22T10:41:47Z",
    "CURRENT_ETOR_TEXT": "2026-04-22T22:30:00Z"
   },
   "geometry": {
    "x": -13517141.855999999,
    "y": 4605222.0236999989
   }
  },
  {
   "attributes": {
    "OUTAGE_ID": "230098",
    "CURRENT_ETOR": 1776891600000,
    "OUTAGE_START": 1776808413000,
    "EST_CUSTOMERS": 1,
    "OUTAGE_CAUSE": "REPLCE TXFMR",
    "CREW_CURRENT_STATUS": "Crew On Site",
    "LAST_UPDATE": 1776871637000,
    "OUTAGE_START_TEXT": "2026-04-21T21:53:33Z",
    "LAST_UPDATE_TEXT": "2026-04-22T15:27:17Z",
    "CURRENT_ETOR_TEXT": "2026-04-22T21:00:00Z"
   },
   "geometry": {
    "x": -13459071.1753,
    "y": 4593660.0006000027
   }
  },
  {
   "attributes": {
    "OUTAGE_ID": "230118",
    "CURRENT_ETOR": 1776880800000,
    "OUTAGE_START": 1776805361000,
    "EST_CUSTOMERS": 8,
    "OUTAGE_CAUSE": "REPLCE TXFMR",
    "CREW_CURRENT_STATUS": "Awaiting Crew",
    "LAST_UPDATE": 1776828896000,
    "OUTAGE_START_TEXT": "2026-04-21T21:02:41Z",
    "LAST_UPDATE_TEXT": "2026-04-22T03:34:56Z",
    "CURRENT_ETOR_TEXT": "2026-04-22T18:00:00Z"
   },
   "geometry": {
    "x": -13470253.7358,
    "y": 4550521.5415000021
   }
  },
  {
   "attributes": {
    "OUTAGE_ID": "230119",
    "CURRENT_ETOR": 1776880800000,
    "OUTAGE_START": 1776805320000,
    "EST_CUSTOMERS": 3,
    "OUTAGE_CAUSE": "REPLCE TXFMR",
    "CREW_CURRENT_STATUS": "Awaiting Crew",
    "LAST_UPDATE": 1776828843000,
    "OUTAGE_START_TEXT": "2026-04-21T21:02:00Z",
    "LAST_UPDATE_TEXT": "2026-04-22T03:34:03Z",
    "CURRENT_ETOR_TEXT": "2026-04-22T18:00:00Z"
   },
   "geometry": {
    "x": -13470216.8917,
    "y": 4550667.1697999984
   }
  },
  {
   "attributes": {
    "OUTAGE_ID": "230122",
    "CURRENT_ETOR": 1776898800000,
    "OUTAGE_START": 1776805500000,
    "EST_CUSTOMERS": 75,
    "OUTAGE_CAUSE": "BRKN UG EQUIPMNT",
    "CREW_CURRENT_STATUS": "Crew Enroute",
    "LAST_UPDATE": 1776865824000,
    "OUTAGE_START_TEXT": "2026-04-21T21:05:00Z",
    "LAST_UPDATE_TEXT": "2026-04-22T13:50:24Z",
    "CURRENT_ETOR_TEXT": "2026-04-22T23:00:00Z"
   },
   "geometry": {
    "x": -13470464.6755,
    "y": 4550794.621299997
   }
  },
  {
   "attributes": {
    "OUTAGE_ID": "230174",
    "CURRENT_ETOR": 1776897000000,
    "OUTAGE_START": 1776809898000,
    "EST_CUSTOMERS": 1,
    "OUTAGE_CAUSE": "REPLCE TXFMR",
    "CREW_CURRENT_STATUS": "Awaiting Crew",
    "LAST_UPDATE": 1776863629000,
    "OUTAGE_START_TEXT": "2026-04-21T22:18:18Z",
    "LAST_UPDATE_TEXT": "2026-04-22T13:13:49Z",
    "CURRENT_ETOR_TEXT": "2026-04-22T22:30:00Z"
   },
   "geometry": {
    "x": -13509045.8902,
    "y": 4607325.1319999993
   }
  },
  {
   "attributes": {
    "OUTAGE_ID": "230222",
    "CURRENT_ETOR": 1776897000000,
    "OUTAGE_START": 1776810275000,
    "EST_CUSTOMERS": 2,
    "OUTAGE_CAUSE": "EMERG REPAIRS",
    "CREW_CURRENT_STATUS": "Crew Enroute",
    "LAST_UPDATE": 1776831440000,
    "OUTAGE_START_TEXT": "2026-04-21T22:24:35Z",
    "LAST_UPDATE_TEXT": "2026-04-22T04:17:20Z",
    "CURRENT_ETOR_TEXT": "2026-04-22T22:30:00Z"
   },
   "geometry": {
    "x": -13510188.963100001,
    "y": 4596786.6948999986
   }
  },
  {
   "attributes": {
    "OUTAGE_ID": "230232",
    "CURRENT_ETOR": 1776897000000,
    "OUTAGE_START": 1776810588000,
    "EST_CUSTOMERS": 1,
    "OUTAGE_CAUSE": "REPLCE TXFMR",
    "CREW_CURRENT_STATUS": "Crew Enroute",
    "LAST_UPDATE": 1776831490000,
    "OUTAGE_START_TEXT": "2026-04-21T22:29:48Z",
    "LAST_UPDATE_TEXT": "2026-04-22T04:18:10Z",
    "CURRENT_ETOR_TEXT": "2026-04-22T22:30:00Z"
   },
   "geometry": {
    "x": -13510551.932799999,
    "y": 4596743.6018999964
   }
  },
  {
   "attributes": {
    "OUTAGE_ID": "230238",
    "CURRENT_ETOR": 1776897000000,
    "OUTAGE_START": 1776810950000,
    "EST_CUSTOMERS": 1,
    "OUTAGE_CAUSE": "EMERG REPAIRS",
    "CREW_CURRENT_STATUS": "Awaiting Crew",
    "LAST_UPDATE": 1776829981000,
    "OUTAGE_START_TEXT": "2026-04-21T22:35:50Z",
    "LAST_UPDATE_TEXT": "2026-04-22T03:53:01Z",
    "CURRENT_ETOR_TEXT": "2026-04-22T22:30:00Z"
   },
   "geometry": {
    "x": -13512697.505100001,
    "y": 4600105.2268999964
   }
  },
  {
   "attributes": {
    "OUTAGE_ID": "230263",
    "CURRENT_ETOR": 1776884400000,
    "OUTAGE_START": 1776811858000,
    "EST_CUSTOMERS": 2,
    "OUTAGE_CAUSE": "REPLCE TXFMR",
    "CREW_CURRENT_STATUS": "Crew On Site",
    "LAST_UPDATE": 1776871722000,
    "OUTAGE_START_TEXT": "2026-04-21T22:50:58Z",
    "LAST_UPDATE_TEXT": "2026-04-22T15:28:42Z",
    "CURRENT_ETOR_TEXT": "2026-04-22T19:00:00Z"
   },
   "geometry": {
    "x": -13453941.1592,
    "y": 4601634.6860999987
   }
  },
  {
   "attributes": {
    "OUTAGE_ID": "230314",
    "CURRENT_ETOR": 1776897000000,
    "OUTAGE_START": 1776798720000,
    "EST_CUSTOMERS": 6,
    "OUTAGE_CAUSE": "REPLCE TXFMR",
    "CREW_CURRENT_STATUS": "Awaiting Crew",
    "LAST_UPDATE": 1776829981000,
    "OUTAGE_START_TEXT": "2026-04-21T19:12:00Z",
    "LAST_UPDATE_TEXT": "2026-04-22T03:53:01Z",
    "CURRENT_ETOR_TEXT": "2026-04-22T22:30:00Z"
   },
   "geometry": {
    "x": -13500204.462200001,
    "y": 4575629.9909999967
   }
  },
  {
   "attributes": {
    "OUTAGE_ID": "230359",
    "CURRENT_ETOR": 1776897000000,
    "OUTAGE_START": 1776815618000,
    "EST_CUSTOMERS": 12,
    "OUTAGE_CAUSE": "STORM",
    "CREW_CURRENT_STATUS": "Awaiting T-Man",
    "LAST_UPDATE": 1776856727000,
    "OUTAGE_START_TEXT": "2026-04-21T23:53:38Z",
    "LAST_UPDATE_TEXT": "2026-04-22T11:18:47Z",
    "CURRENT_ETOR_TEXT": "2026-04-22T22:30:00Z"
   },
   "geometry": {
    "x": -13500231.404300001,
    "y": 4575701.4693000019
   }
  },
  {
   "attributes": {
    "OUTAGE_ID": "230378",
    "CURRENT_ETOR": 1776897960000,
    "OUTAGE_START": 1776815932000,
    "EST_CUSTOMERS": 1,
    "OUTAGE_CAUSE": "REPLCE TXFMR",
    "CREW_CURRENT_STATUS": "Awaiting Crew",
    "LAST_UPDATE": 1776833235000,
    "OUTAGE_START_TEXT": "2026-04-21T23:58:52Z",
    "LAST_UPDATE_TEXT": "2026-04-22T04:47:15Z",
    "CURRENT_ETOR_TEXT": "2026-04-22T22:46:00Z"
   },
   "geometry": {
    "x": -13393031.638,
    "y": 4446936.3137999997
   }
  },
  {
   "attributes": {
    "OUTAGE_ID": "230408",
    "CURRENT_ETOR": 1776897000000,
    "OUTAGE_START": 1776816211000,
    "EST_CUSTOMERS": 1,
    "OUTAGE_CAUSE": "EMERG REPAIRS",
    "CREW_CURRENT_STATUS": "Awaiting Crew",
    "LAST_UPDATE": 1776829981000,
    "OUTAGE_START_TEXT": "2026-04-22T00:03:31Z",
    "LAST_UPDATE_TEXT": "2026-04-22T03:53:01Z",
    "CURRENT_ETOR_TEXT": "2026-04-22T22:30:00Z"
   },
   "geometry": {
    "x": -13472400.297600001,
    "y": 4601090.9001000002
   }
  },
  {
   "attributes": {
    "OUTAGE_ID": "230409",
    "CURRENT_ETOR": 1776897000000,
    "OUTAGE_START": 1776812400000,
    "EST_CUSTOMERS": 2,
    "OUTAGE_CAUSE": "REPLCE TXFMR",
    "CREW_CURRENT_STATUS": "Crew On Site",
    "LAST_UPDATE": 1776829982000,
    "OUTAGE_START_TEXT": "2026-04-21T23:00:00Z",
    "LAST_UPDATE_TEXT": "2026-04-22T03:53:02Z",
    "CURRENT_ETOR_TEXT": "2026-04-22T22:30:00Z"
   },
   "geometry": {
    "x": -13498787.445,
    "y": 4579411.2422999963
   }
  },
  {
   "attributes": {
    "OUTAGE_ID": "230412",
    "CURRENT_ETOR": 1776897000000,
    "OUTAGE_START": 1776805020000,
    "EST_CUSTOMERS": 2,
    "OUTAGE_CAUSE": "REPLCE TXFMR",
    "CREW_CURRENT_STATUS": "Awaiting Crew",
    "LAST_UPDATE": 1776829982000,
    "OUTAGE_START_TEXT": "2026-04-21T20:57:00Z",
    "LAST_UPDATE_TEXT": "2026-04-22T03:53:02Z",
    "CURRENT_ETOR_TEXT": "2026-04-22T22:30:00Z"
   },
   "geometry": {
    "x": -13468535.811900001,
    "y": 4579506.067900002
   }
  },
  {
   "attributes": {
    "OUTAGE_ID": "230425",
    "CURRENT_ETOR": 1776898800000,
    "OUTAGE_START": 1776816514000,
    "EST_CUSTOMERS": 11,
    "OUTAGE_CAUSE": "EMERG REPAIRS",
    "CREW_CURRENT_STATUS": "Awaiting Crew",
    "LAST_UPDATE": 1776866466000,
    "OUTAGE_START_TEXT": "2026-04-22T00:08:34Z",
    "LAST_UPDATE_TEXT": "2026-04-22T14:01:06Z",
    "CURRENT_ETOR_TEXT": "2026-04-22T23:00:00Z"
   },
   "geometry": {
    "x": -13408712.1032,
    "y": 4418993.5204999968
   }
  },
  {
   "attributes": {
    "OUTAGE_ID": "230458",
    "CURRENT_ETOR": 1776880800000,
    "OUTAGE_START": 1776817547000,
    "EST_CUSTOMERS": 1,
    "OUTAGE_CAUSE": "REPLCE TXFMR",
    "CREW_CURRENT_STATUS": "Awaiting Crew",
    "LAST_UPDATE": 1776825866000,
    "OUTAGE_START_TEXT": "2026-04-22T00:25:47Z",
    "LAST_UPDATE_TEXT": "2026-04-22T02:44:26Z",
    "CURRENT_ETOR_TEXT": "2026-04-22T18:00:00Z"
   },
   "geometry": {
    "x": -13457041.551899999,
    "y": 4545264.4151000008
   }
  },
  {
   "attributes": {
    "OUTAGE_ID": "230464",
    "CURRENT_ETOR": 1776897000000,
    "OUTAGE_START": 1776818040000,
    "EST_CUSTOMERS": 2,
    "OUTAGE_CAUSE": "REPLCE TXFMR",
    "CREW_CURRENT_STATUS": "Awaiting Crew",
    "LAST_UPDATE": 1776829982000,
    "OUTAGE_START_TEXT": "2026-04-22T00:34:00Z",
    "LAST_UPDATE_TEXT": "2026-04-22T03:53:02Z",
    "CURRENT_ETOR_TEXT": "2026-04-22T22:30:00Z"
   },
   "geometry": {
    "x": -13498923.1996,
    "y": 4579410.7377000004
   }
  },
  {
   "attributes": {
    "OUTAGE_ID": "230468",
    "CURRENT_ETOR": 1776889800000,
    "OUTAGE_START": 1776818197000,
    "EST_CUSTOMERS": 4,
    "OUTAGE_CAUSE": "REPLCE TXFMR",
    "CREW_CURRENT_STATUS": "Awaiting Crew",
    "LAST_UPDATE": 1776865286000,
    "OUTAGE_START_TEXT": "2026-04-22T00:36:37Z",
    "LAST_UPDATE_TEXT": "2026-04-22T13:41:26Z",
    "CURRENT_ETOR_TEXT": "2026-04-22T20:30:00Z"
   },
   "geometry": {
    "x": -13412481.897599999,
    "y": 4429431.2643000036
   }
  },
  {
   "attributes": {
    "OUTAGE_ID": "230476",
    "CURRENT_ETOR": 1776898800000,
    "OUTAGE_START": 1776819264000,
    "EST_CUSTOMERS": 1,
    "OUTAGE_CAUSE": "REPLCE TXFMR",
    "CREW_CURRENT_STATUS": "Awaiting Crew",
    "LAST_UPDATE": 1776830626000,
    "OUTAGE_START_TEXT": "2026-04-22T00:54:24Z",
    "LAST_UPDATE_TEXT": "2026-04-22T04:03:46Z",
    "CURRENT_ETOR_TEXT": "2026-04-22T23:00:00Z"
   },
   "geometry": {
    "x": -13378495.332800001,
    "y": 4430113.4672999978
   }
  },
  {
   "attributes": {
    "OUTAGE_ID": "230478",
    "CURRENT_ETOR": 1776889800000,
    "OUTAGE_START": 1776819299000,
    "EST_CUSTOMERS": 3,
    "OUTAGE_CAUSE": "REPLCE TXFMR",
    "CREW_CURRENT_STATUS": "Awaiting Crew",
    "LAST_UPDATE": 1776865337000,
    "OUTAGE_START_TEXT": "2026-04-22T00:54:59Z",
    "LAST_UPDATE_TEXT": "2026-04-22T13:42:17Z",
    "CURRENT_ETOR_TEXT": "2026-04-22T20:30:00Z"
   },
   "geometry": {
    "x": -13412521.4048,
    "y": 4429329.4368000031
   }
  },
  {
   "attributes": {
    "OUTAGE_ID": "230479",
    "CURRENT_ETOR": null,
    "OUTAGE_START": 1776819317000,
    "EST_CUSTOMERS": 2,
    "OUTAGE_CAUSE": "REPLCE TXFMR",
    "CREW_CURRENT_STATUS": "Awaiting Crew",
    "LAST_UPDATE": 1776853093000,
    "OUTAGE_START_TEXT": "2026-04-22T00:55:17Z",
    "LAST_UPDATE_TEXT": "2026-04-22T10:18:13Z",
    "CURRENT_ETOR_TEXT": null
   },
   "geometry": {
    "x": -13459648.091400001,
    "y": 4549076.3306000009
   }
  },
  {
   "attributes": {
    "OUTAGE_ID": "230496",
    "CURRENT_ETOR": 1776897000000,
    "OUTAGE_START": 1776818040000,
    "EST_CUSTOMERS": 1,
    "OUTAGE_CAUSE": "REPLCE TXFMR",
    "CREW_CURRENT_STATUS": "Awaiting Crew",
    "LAST_UPDATE": 1776829982000,
    "OUTAGE_START_TEXT": "2026-04-22T00:34:00Z",
    "LAST_UPDATE_TEXT": "2026-04-22T03:53:02Z",
    "CURRENT_ETOR_TEXT": "2026-04-22T22:30:00Z"
   },
   "geometry": {
    "x": -13498906.7755,
    "y": 4579539.0909999982
   }
  },
  {
   "attributes": {
    "OUTAGE_ID": "230501",
    "CURRENT_ETOR": 1776895200000,
    "OUTAGE_START": 1776820859000,
    "EST_CUSTOMERS": 1,
    "OUTAGE_CAUSE": "BRKN POLE",
    "CREW_CURRENT_STATUS": "Awaiting Crew",
    "LAST_UPDATE": 1776870027000,
    "OUTAGE_START_TEXT": "2026-04-22T01:20:59Z",
    "LAST_UPDATE_TEXT": "2026-04-22T15:00:27Z",
    "CURRENT_ETOR_TEXT": "2026-04-22T22:00:00Z"
   },
   "geometry": {
    "x": -13551107.3444,
    "y": 4439758.2465000004
   }
  },
  {
   "attributes": {
    "OUTAGE_ID": "230503",
    "CURRENT_ETOR": 1776897000000,
    "OUTAGE_START": 1776819533000,
    "EST_CUSTOMERS": 2,
    "OUTAGE_CAUSE": "EMERG REPAIRS",
    "CREW_CURRENT_STATUS": "Awaiting Crew",
    "LAST_UPDATE": 1776829982000,
    "OUTAGE_START_TEXT": "2026-04-22T00:58:53Z",
    "LAST_UPDATE_TEXT": "2026-04-22T03:53:02Z",
    "CURRENT_ETOR_TEXT": "2026-04-22T22:30:00Z"
   },
   "geometry": {
    "x": -13510552.376899999,
    "y": 4596786.3687999994
   }
  },
  {
   "attributes": {
    "OUTAGE_ID": "230531",
    "CURRENT_ETOR": 1776893400000,
    "OUTAGE_START": 1776822060000,
    "EST_CUSTOMERS": 1,
    "OUTAGE_CAUSE": "EMERG REPAIRS",
    "CREW_CURRENT_STATUS": "Awaiting Crew",
    "LAST_UPDATE": 1776868692000,
    "OUTAGE_START_TEXT": "2026-04-22T01:41:00Z",
    "LAST_UPDATE_TEXT": "2026-04-22T14:38:12Z",
    "CURRENT_ETOR_TEXT": "2026-04-22T21:30:00Z"
   },
   "geometry": {
    "x": -13570663.907,
    "y": 4470302.5524000004
   }
  },
  {
   "attributes": {
    "OUTAGE_ID": "230548",
    "CURRENT_ETOR": 1776870000000,
    "OUTAGE_START": 1776824560000,
    "EST_CUSTOMERS": 18,
    "OUTAGE_CAUSE": "DAMGE UG CABLE",
    "CREW_CURRENT_STATUS": "Crew On Site",
    "LAST_UPDATE": 1776858963000,
    "OUTAGE_START_TEXT": "2026-04-22T02:22:40Z",
    "LAST_UPDATE_TEXT": "2026-04-22T11:56:03Z",
    "CURRENT_ETOR_TEXT": "2026-04-22T15:00:00Z"
   },
   "geometry": {
    "x": -13580951.433600001,
    "y": 4433986.9930000007
   }
  },
  {
   "attributes": {
    "OUTAGE_ID": "230550",
    "CURRENT_ETOR": 1776897000000,
    "OUTAGE_START": 1776803235000,
    "EST_CUSTOMERS": 2,
    "OUTAGE_CAUSE": "EMERG REPAIRS",
    "CREW_CURRENT_STATUS": "Awaiting Crew",
    "LAST_UPDATE": 1776829982000,
    "OUTAGE_START_TEXT": "2026-04-21T20:27:15Z",
    "LAST_UPDATE_TEXT": "2026-04-22T03:53:02Z",
    "CURRENT_ETOR_TEXT": "2026-04-22T22:30:00Z"
   },
   "geometry": {
    "x": -13472400.297600001,
    "y": 4601090.9001000002
   }
  },
  {
   "attributes": {
    "OUTAGE_ID": "230553",
    "CURRENT_ETOR": null,
    "OUTAGE_START": 1776825495000,
    "EST_CUSTOMERS": 1,
    "OUTAGE_CAUSE": "REPLCE TXFMR",
    "CREW_CURRENT_STATUS": "Awaiting Crew",
    "LAST_UPDATE": 1776853132000,
    "OUTAGE_START_TEXT": "2026-04-22T02:38:15Z",
    "LAST_UPDATE_TEXT": "2026-04-22T10:18:52Z",
    "CURRENT_ETOR_TEXT": null
   },
   "geometry": {
    "x": -13395171.6503,
    "y": 4441899.0253000036
   }
  },
  {
   "attributes": {
    "OUTAGE_ID": "230559",
    "CURRENT_ETOR": 1776909600000,
    "OUTAGE_START": 1776826610000,
    "EST_CUSTOMERS": 1,
    "OUTAGE_CAUSE": "REPLCE TXFMR",
    "CREW_CURRENT_STATUS": "Awaiting Crew",
    "LAST_UPDATE": 1776834556000,
    "OUTAGE_START_TEXT": "2026-04-22T02:56:50Z",
    "LAST_UPDATE_TEXT": "2026-04-22T05:09:16Z",
    "CURRENT_ETOR_TEXT": "2026-04-23T02:00:00Z"
   },
   "geometry": {
    "x": -13454613.538699999,
    "y": 4541687.8772
   }
  },
  {
   "attributes": {
    "OUTAGE_ID": "230561",
    "CURRENT_ETOR": 1776898800000,
    "OUTAGE_START": 1776826860000,
    "EST_CUSTOMERS": 2,
    "OUTAGE_CAUSE": "REPLCE TXFMR",
    "CREW_CURRENT_STATUS": "Awaiting Crew",
    "LAST_UPDATE": 1776830006000,
    "OUTAGE_START_TEXT": "2026-04-22T03:01:00Z",
    "LAST_UPDATE_TEXT": "2026-04-22T03:53:26Z",
    "CURRENT_ETOR_TEXT": "2026-04-22T23:00:00Z"
   },
   "geometry": {
    "x": -13473034.372299999,
    "y": 4548736.6432000026
   }
  },
  {
   "attributes": {
    "OUTAGE_ID": "230564",
    "CURRENT_ETOR": null,
    "OUTAGE_START": 1776827007000,
    "EST_CUSTOMERS": 1,
    "OUTAGE_CAUSE": "Awaiting Investigation",
    "CREW_CURRENT_STATUS": "No Access",
    "LAST_UPDATE": 1776848610000,
    "OUTAGE_START_TEXT": "2026-04-22T03:03:27Z",
    "LAST_UPDATE_TEXT": "2026-04-22T09:03:30Z",
    "CURRENT_ETOR_TEXT": null
   },
   "geometry": {
    "x": -13399281.0616,
    "y": 4427610.0706999972
   }
  },
  {
   "attributes": {
    "OUTAGE_ID": "230572",
    "CURRENT_ETOR": 1776897000000,
    "OUTAGE_START": 1776827702000,
    "EST_CUSTOMERS": 1,
    "OUTAGE_CAUSE": "REPLCE TXFMR",
    "CREW_CURRENT_STATUS": "Awaiting Crew",
    "LAST_UPDATE": 1776831624000,
    "OUTAGE_START_TEXT": "2026-04-22T03:15:02Z",
    "LAST_UPDATE_TEXT": "2026-04-22T04:20:24Z",
    "CURRENT_ETOR_TEXT": "2026-04-22T22:30:00Z"
   },
   "geometry": {
    "x": -13512895.57,
    "y": 4600594.3759000003
   }
  },
  {
   "attributes": {
    "OUTAGE_ID": "230573",
    "CURRENT_ETOR": 1776897000000,
    "OUTAGE_START": 1776827750000,
    "EST_CUSTOMERS": 1,
    "OUTAGE_CAUSE": "REPLCE TXFMR",
    "CREW_CURRENT_STATUS": "Awaiting Crew",
    "LAST_UPDATE": 1776831624000,
    "OUTAGE_START_TEXT": "2026-04-22T03:15:50Z",
    "LAST_UPDATE_TEXT": "2026-04-22T04:20:24Z",
    "CURRENT_ETOR_TEXT": "2026-04-22T22:30:00Z"
   },
   "geometry": {
    "x": -13512697.505100001,
    "y": 4600105.2268999964
   }
  },
  {
   "attributes": {
    "OUTAGE_ID": "230574",
    "CURRENT_ETOR": 1776897000000,
    "OUTAGE_START": 1776803543000,
    "EST_CUSTOMERS": 3,
    "OUTAGE_CAUSE": "REPLCE TXFMR",
    "CREW_CURRENT_STATUS": "Awaiting Crew",
    "LAST_UPDATE": 1776831411000,
    "OUTAGE_START_TEXT": "2026-04-21T20:32:23Z",
    "LAST_UPDATE_TEXT": "2026-04-22T04:16:51Z",
    "CURRENT_ETOR_TEXT": "2026-04-22T22:30:00Z"
   },
   "geometry": {
    "x": -13472683.709100001,
    "y": 4601088.5732999966
   }
  },
  {
   "attributes": {
    "OUTAGE_ID": "230579",
    "CURRENT_ETOR": 1776898800000,
    "OUTAGE_START": 1776827964000,
    "EST_CUSTOMERS": 2,
    "OUTAGE_CAUSE": "REPLCE TXFMR",
    "CREW_CURRENT_STATUS": "Awaiting Crew",
    "LAST_UPDATE": 1776831507000,
    "OUTAGE_START_TEXT": "2026-04-22T03:19:24Z",
    "LAST_UPDATE_TEXT": "2026-04-22T04:18:27Z",
    "CURRENT_ETOR_TEXT": "2026-04-22T23:00:00Z"
   },
   "geometry": {
    "x": -13472901.6472,
    "y": 4548732.3836999983
   }
  },
  {
   "attributes": {
    "OUTAGE_ID": "230580",
    "CURRENT_ETOR": 1776898800000,
    "OUTAGE_START": 1776826860000,
    "EST_CUSTOMERS": 1,
    "OUTAGE_CAUSE": "REPLCE TXFMR",
    "CREW_CURRENT_STATUS": "Awaiting Crew",
    "LAST_UPDATE": 1776831527000,
    "OUTAGE_START_TEXT": "2026-04-22T03:01:00Z",
    "LAST_UPDATE_TEXT": "2026-04-22T04:18:47Z",
    "CURRENT_ETOR_TEXT": "2026-04-22T23:00:00Z"
   },
   "geometry": {
    "x": -13472642.898400001,
    "y": 4548422.0287000015
   }
  },
  {
   "attributes": {
    "OUTAGE_ID": "230583",
    "CURRENT_ETOR": 1776898800000,
    "OUTAGE_START": 1776826860000,
    "EST_CUSTOMERS": 3,
    "OUTAGE_CAUSE": "REPLCE TXFMR",
    "CREW_CURRENT_STATUS": "Awaiting Crew",
    "LAST_UPDATE": 1776834522000,
    "OUTAGE_START_TEXT": "2026-04-22T03:01:00Z",
    "LAST_UPDATE_TEXT": "2026-04-22T05:08:42Z",
    "CURRENT_ETOR_TEXT": "2026-04-22T23:00:00Z"
   },
   "geometry": {
    "x": -13472552.2356,
    "y": 4548470.0173999965
   }
  },
  {
   "attributes": {
    "OUTAGE_ID": "230609",
    "CURRENT_ETOR": 1776877200000,
    "OUTAGE_START": 1776830280000,
    "EST_CUSTOMERS": 1,
    "OUTAGE_CAUSE": "REPLCE TXFMR",
    "CREW_CURRENT_STATUS": "Crew Enroute",
    "LAST_UPDATE": 1776843979000,
    "OUTAGE_START_TEXT": "2026-04-22T03:58:00Z",
    "LAST_UPDATE_TEXT": "2026-04-22T07:46:19Z",
    "CURRENT_ETOR_TEXT": "2026-04-22T17:00:00Z"
   },
   "geometry": {
    "x": -13533452.210900001,
    "y": 4810563.1235999987
   }
  },
  {
   "attributes": {
    "OUTAGE_ID": "230610",
    "CURRENT_ETOR": 1776874500000,
    "OUTAGE_START": 1776830423000,
    "EST_CUSTOMERS": 1,
    "OUTAGE_CAUSE": "PATROLLING",
    "CREW_CURRENT_STATUS": "T-Man On Site",
    "LAST_UPDATE": 1776865602000,
    "OUTAGE_START_TEXT": "2026-04-22T04:00:23Z",
    "LAST_UPDATE_TEXT": "2026-04-22T13:46:42Z",
    "CURRENT_ETOR_TEXT": "2026-04-22T16:15:00Z"
   },
   "geometry": {
    "x": -13559950.480599999,
    "y": 4444505.4671000019
   }
  },
  {
   "attributes": {
    "OUTAGE_ID": "230617",
    "CURRENT_ETOR": 1776848400000,
    "OUTAGE_START": 1776830494000,
    "EST_CUSTOMERS": 57,
    "OUTAGE_CAUSE": "PLNND SHUTDOWN",
    "CREW_CURRENT_STATUS": "Awaiting Crew",
    "LAST_UPDATE": 1776845270000,
    "OUTAGE_START_TEXT": "2026-04-22T04:01:34Z",
    "LAST_UPDATE_TEXT": "2026-04-22T08:07:50Z",
    "CURRENT_ETOR_TEXT": "2026-04-22T09:00:00Z"
   },
   "geometry": {
    "x": -13635955.916999999,
    "y": 4547406.5795999989
   }
  },
  {
   "attributes": {
    "OUTAGE_ID": "230626",
    "CURRENT_ETOR": 1776897000000,
    "OUTAGE_START": 1776832320000,
    "EST_CUSTOMERS": 1,
    "OUTAGE_CAUSE": "REPLCE TXFMR",
    "CREW_CURRENT_STATUS": "Awaiting Crew",
    "LAST_UPDATE": 1776863646000,
    "OUTAGE_START_TEXT": "2026-04-22T04:32:00Z",
    "LAST_UPDATE_TEXT": "2026-04-22T13:14:06Z",
    "CURRENT_ETOR_TEXT": "2026-04-22T22:30:00Z"
   },
   "geometry": {
    "x": -13470191.991599999,
    "y": 4580293.2176999971
   }
  },
  {
   "attributes": {
    "OUTAGE_ID": "230629",
    "CURRENT_ETOR": 1776898800000,
    "OUTAGE_START": 1776832500000,
    "EST_CUSTOMERS": 2,
    "OUTAGE_CAUSE": "REPLCE TXFMR",
    "CREW_CURRENT_STATUS": "Awaiting Crew",
    "LAST_UPDATE": 1776834586000,
    "OUTAGE_START_TEXT": "2026-04-22T04:35:00Z",
    "LAST_UPDATE_TEXT": "2026-04-22T05:09:46Z",
    "CURRENT_ETOR_TEXT": "2026-04-22T23:00:00Z"
   },
   "geometry": {
    "x": -13427899.8224,
    "y": 4501950.686300002
   }
  },
  {
   "attributes": {
    "OUTAGE_ID": "230633",
    "CURRENT_ETOR": null,
    "OUTAGE_START": 1776833873000,
    "EST_CUSTOMERS": 34,
    "OUTAGE_CAUSE": "Awaiting Investigation",
    "CREW_CURRENT_STATUS": "T-Man On Site",
    "LAST_UPDATE": 1776869525000,
    "OUTAGE_START_TEXT": "2026-04-22T04:57:53Z",
    "LAST_UPDATE_TEXT": "2026-04-22T14:52:05Z",
    "CURRENT_ETOR_TEXT": null
   },
   "geometry": {
    "x": -13256283.2588,
    "y": 4405815.4975000024
   }
  },
  {
   "attributes": {
    "OUTAGE_ID": "230635",
    "CURRENT_ETOR": 1776895200000,
    "OUTAGE_START": 1776834572000,
    "EST_CUSTOMERS": 2,
    "OUTAGE_CAUSE": "REPLCE TXFMR",
    "CREW_CURRENT_STATUS": "Awaiting Crew",
    "LAST_UPDATE": 1776867351000,
    "OUTAGE_START_TEXT": "2026-04-22T05:09:32Z",
    "LAST_UPDATE_TEXT": "2026-04-22T14:15:51Z",
    "CURRENT_ETOR_TEXT": "2026-04-22T22:00:00Z"
   },
   "geometry": {
    "x": -13602125.980700001,
    "y": 4834819.005400002
   }
  },
  {
   "attributes": {
    "OUTAGE_ID": "230636",
    "CURRENT_ETOR": 1776897000000,
    "OUTAGE_START": 1776803760000,
    "EST_CUSTOMERS": 3,
    "OUTAGE_CAUSE": "EMERG REPAIRS",
    "CREW_CURRENT_STATUS": "Awaiting Crew",
    "LAST_UPDATE": 1776836735000,
    "OUTAGE_START_TEXT": "2026-04-21T20:36:00Z",
    "LAST_UPDATE_TEXT": "2026-04-22T05:45:35Z",
    "CURRENT_ETOR_TEXT": "2026-04-22T22:30:00Z"
   },
   "geometry": {
    "x": -13498809.7722,
    "y": 4579753.5786999986
   }
  },
  {
   "attributes": {
    "OUTAGE_ID": "230645",
    "CURRENT_ETOR": 1776870900000,
    "OUTAGE_START": 1776829380000,
    "EST_CUSTOMERS": 47,
    "OUTAGE_CAUSE": null,
    "CREW_CURRENT_STATUS": "Awaiting T-Man",
    "LAST_UPDATE": 1776871315000,
    "OUTAGE_START_TEXT": "2026-04-22T03:43:00Z",
    "LAST_UPDATE_TEXT": "2026-04-22T15:21:55Z",
    "CURRENT_ETOR_TEXT": "2026-04-22T15:15:00Z"
   },
   "geometry": {
    "x": -13625217.8182,
    "y": 4541282.4478999972
   }
  },
  {
   "attributes": {
    "OUTAGE_ID": "230647",
    "CURRENT_ETOR": 1776871800000,
    "OUTAGE_START": 1776834960000,
    "EST_CUSTOMERS": 24,
    "OUTAGE_CAUSE": null,
    "CREW_CURRENT_STATUS": "Awaiting T-Man",
    "LAST_UPDATE": 1776871345000,
    "OUTAGE_START_TEXT": "2026-04-22T05:16:00Z",
    "LAST_UPDATE_TEXT": "2026-04-22T15:22:25Z",
    "CURRENT_ETOR_TEXT": "2026-04-22T15:30:00Z"
   },
   "geometry": {
    "x": -13625438.336100001,
    "y": 4541419.3950999975
   }
  },
  {
   "attributes": {
    "OUTAGE_ID": "230651",
    "CURRENT_ETOR": 1776864600000,
    "OUTAGE_START": 1776832920000,
    "EST_CUSTOMERS": 1,
    "OUTAGE_CAUSE": "REPLCE TXFMR",
    "CREW_CURRENT_STATUS": "Crew Enroute",
    "LAST_UPDATE": 1776864438000,
    "OUTAGE_START_TEXT": "2026-04-22T04:42:00Z",
    "LAST_UPDATE_TEXT": "2026-04-22T13:27:18Z",
    "CURRENT_ETOR_TEXT": "2026-04-22T13:30:00Z"
   },
   "geometry": {
    "x": -13289378.2344,
    "y": 4433397.2734000012
   }
  },
  {
   "attributes": {
    "OUTAGE_ID": "230656",
    "CURRENT_ETOR": 1776897000000,
    "OUTAGE_START": 1776802966000,
    "EST_CUSTOMERS": 2,
    "OUTAGE_CAUSE": "EMERG REPAIRS",
    "CREW_CURRENT_STATUS": "Awaiting T-Man",
    "LAST_UPDATE": 1776841610000,
    "OUTAGE_START_TEXT": "2026-04-21T20:22:46Z",
    "LAST_UPDATE_TEXT": "2026-04-22T07:06:50Z",
    "CURRENT_ETOR_TEXT": "2026-04-22T22:30:00Z"
   },
   "geometry": {
    "x": -13470840.440299999,
    "y": 4558669.8721999973
   }
  },
  {
   "attributes": {
    "OUTAGE_ID": "230660",
    "CURRENT_ETOR": 1776920400000,
    "OUTAGE_START": 1776831180000,
    "EST_CUSTOMERS": 1,
    "OUTAGE_CAUSE": null,
    "CREW_CURRENT_STATUS": "Awaiting T-Man",
    "LAST_UPDATE": 1776865721000,
    "OUTAGE_START_TEXT": "2026-04-22T04:13:00Z",
    "LAST_UPDATE_TEXT": "2026-04-22T13:48:41Z",
    "CURRENT_ETOR_TEXT": "2026-04-23T05:00:00Z"
   },
   "geometry": {
    "x": -13497873.4387,
    "y": 4346352.6828000024
   }
  },
  {
   "attributes": {
    "OUTAGE_ID": "230675",
    "CURRENT_ETOR": null,
    "OUTAGE_START": 1776844052000,
    "EST_CUSTOMERS": 2,
    "OUTAGE_CAUSE": "REPLCE TXFMR",
    "CREW_CURRENT_STATUS": "Crew Enroute",
    "LAST_UPDATE": 1776856478000,
    "OUTAGE_START_TEXT": "2026-04-22T07:47:32Z",
    "LAST_UPDATE_TEXT": "2026-04-22T11:14:38Z",
    "CURRENT_ETOR_TEXT": null
   },
   "geometry": {
    "x": -13607347.860199999,
    "y": 4835405.9580999985
   }
  },
  {
   "attributes": {
    "OUTAGE_ID": "230676",
    "CURRENT_ETOR": null,
    "OUTAGE_START": 1776843551000,
    "EST_CUSTOMERS": 1,
    "OUTAGE_CAUSE": "REPLCE TXFMR",
    "CREW_CURRENT_STATUS": "Crew Enroute",
    "LAST_UPDATE": 1776856493000,
    "OUTAGE_START_TEXT": "2026-04-22T07:39:11Z",
    "LAST_UPDATE_TEXT": "2026-04-22T11:14:53Z",
    "CURRENT_ETOR_TEXT": null
   },
   "geometry": {
    "x": -13606961.271,
    "y": 4835530.4333999977
   }
  },
  {
   "attributes": {
    "OUTAGE_ID": "230692",
    "CURRENT_ETOR": null,
    "OUTAGE_START": 1776851591000,
    "EST_CUSTOMERS": 17,
    "OUTAGE_CAUSE": "STORM",
    "CREW_CURRENT_STATUS": "Awaiting T-Man",
    "LAST_UPDATE": 1776866010000,
    "OUTAGE_START_TEXT": "2026-04-22T09:53:11Z",
    "LAST_UPDATE_TEXT": "2026-04-22T13:53:30Z",
    "CURRENT_ETOR_TEXT": null
   },
   "geometry": {
    "x": -13496286.9987,
    "y": 4513667.8839000016
   }
  },
  {
   "attributes": {
    "OUTAGE_ID": "230697",
    "CURRENT_ETOR": 1776884400000,
    "OUTAGE_START": 1776853635000,
    "EST_CUSTOMERS": 1,
    "OUTAGE_CAUSE": "EMERG REPAIRS",
    "CREW_CURRENT_STATUS": "Crew On Site",
    "LAST_UPDATE": 1776870121000,
    "OUTAGE_START_TEXT": "2026-04-22T10:27:15Z",
    "LAST_UPDATE_TEXT": "2026-04-22T15:02:01Z",
    "CURRENT_ETOR_TEXT": "2026-04-22T19:00:00Z"
   },
   "geometry": {
    "x": -13658059.159699999,
    "y": 4641422.0495000035
   }
  },
  {
   "attributes": {
    "OUTAGE_ID": "230699",
    "CURRENT_ETOR": 1776895200000,
    "OUTAGE_START": 1776816328000,
    "EST_CUSTOMERS": 4,
    "OUTAGE_CAUSE": "REPLCE TXFMR",
    "CREW_CURRENT_STATUS": "Awaiting Crew",
    "LAST_UPDATE": 1776867295000,
    "OUTAGE_START_TEXT": "2026-04-22T00:05:28Z",
    "LAST_UPDATE_TEXT": "2026-04-22T14:14:55Z",
    "CURRENT_ETOR_TEXT": "2026-04-22T22:00:00Z"
   },
   "geometry": {
    "x": -13590599.9825,
    "y": 4840949.9628000036
   }
  },
  {
   "attributes": {
    "OUTAGE_ID": "230706",
    "CURRENT_ETOR": null,
    "OUTAGE_START": 1776858819000,
    "EST_CUSTOMERS": 1,
    "OUTAGE_CAUSE": "REPLCE TXFMR",
    "CREW_CURRENT_STATUS": "Awaiting Crew",
    "LAST_UPDATE": 1776870572000,
    "OUTAGE_START_TEXT": "2026-04-22T11:53:39Z",
    "LAST_UPDATE_TEXT": "2026-04-22T15:09:32Z",
    "CURRENT_ETOR_TEXT": null
   },
   "geometry": {
    "x": -13605686.423599999,
    "y": 4834894.1376999989
   }
  },
  {
   "attributes": {
    "OUTAGE_ID": "230712",
    "CURRENT_ETOR": null,
    "OUTAGE_START": 1776859665000,
    "EST_CUSTOMERS": 1,
    "OUTAGE_CAUSE": "STORM",
    "CREW_CURRENT_STATUS": "Awaiting T-Man",
    "LAST_UPDATE": 1776861113000,
    "OUTAGE_START_TEXT": "2026-04-22T12:07:45Z",
    "LAST_UPDATE_TEXT": "2026-04-22T12:31:53Z",
    "CURRENT_ETOR_TEXT": null
   },
   "geometry": {
    "x": -13410780.465300001,
    "y": 4450468.9660999998
   }
  },
  {
   "attributes": {
    "OUTAGE_ID": "230717",
    "CURRENT_ETOR": null,
    "OUTAGE_START": 1776861141000,
    "EST_CUSTOMERS": 30,
    "OUTAGE_CAUSE": "STORM",
    "CREW_CURRENT_STATUS": "T-Man Enroute",
    "LAST_UPDATE": 1776865576000,
    "OUTAGE_START_TEXT": "2026-04-22T12:32:21Z",
    "LAST_UPDATE_TEXT": "2026-04-22T13:46:16Z",
    "CURRENT_ETOR_TEXT": null
   },
   "geometry": {
    "x": -13265344.5021,
    "y": 4399074.1955000013
   }
  },
  {
   "attributes": {
    "OUTAGE_ID": "230718",
    "CURRENT_ETOR": 1776889800000,
    "OUTAGE_START": 1776862181000,
    "EST_CUSTOMERS": 1,
    "OUTAGE_CAUSE": "PATROLLING",
    "CREW_CURRENT_STATUS": "T-Man On Site",
    "LAST_UPDATE": 1776864223000,
    "OUTAGE_START_TEXT": "2026-04-22T12:49:41Z",
    "LAST_UPDATE_TEXT": "2026-04-22T13:23:43Z",
    "CURRENT_ETOR_TEXT": "2026-04-22T20:30:00Z"
   },
   "geometry": {
    "x": -13584215.283,
    "y": 4474798.6054000035
   }
  },
  {
   "attributes": {
    "OUTAGE_ID": "230719",
    "CURRENT_ETOR": 1776893400000,
    "OUTAGE_START": 1776862838000,
    "EST_CUSTOMERS": 1,
    "OUTAGE_CAUSE": null,
    "CREW_CURRENT_STATUS": "Awaiting T-Man",
    "LAST_UPDATE": 1776862844000,
    "OUTAGE_START_TEXT": "2026-04-22T13:00:38Z",
    "LAST_UPDATE_TEXT": "2026-04-22T13:00:44Z",
    "CURRENT_ETOR_TEXT": "2026-04-22T21:30:00Z"
   },
   "geometry": {
    "x": -13641491.7195,
    "y": 4565285.493900001
   }
  },
  {
   "attributes": {
    "OUTAGE_ID": "230720",
    "CURRENT_ETOR": null,
    "OUTAGE_START": 1776863009000,
    "EST_CUSTOMERS": 1,
    "OUTAGE_CAUSE": "STORM",
    "CREW_CURRENT_STATUS": "T-Man Enroute",
    "LAST_UPDATE": 1776863014000,
    "OUTAGE_START_TEXT": "2026-04-22T13:03:29Z",
    "LAST_UPDATE_TEXT": "2026-04-22T13:03:34Z",
    "CURRENT_ETOR_TEXT": null
   },
   "geometry": {
    "x": -13608777.3475,
    "y": 4832381.9588000029
   }
  },
  {
   "attributes": {
    "OUTAGE_ID": "230724",
    "CURRENT_ETOR": 1776877200000,
    "OUTAGE_START": 1776863910000,
    "EST_CUSTOMERS": 1,
    "OUTAGE_CAUSE": "PATROLLING",
    "CREW_CURRENT_STATUS": "T-Man On Site",
    "LAST_UPDATE": 1776870304000,
    "OUTAGE_START_TEXT": "2026-04-22T13:18:30Z",
    "LAST_UPDATE_TEXT": "2026-04-22T15:05:04Z",
    "CURRENT_ETOR_TEXT": "2026-04-22T17:00:00Z"
   },
   "geometry": {
    "x": -13451337.2226,
    "y": 4207670.3369000033
   }
  },
  {
   "attributes": {
    "OUTAGE_ID": "230725",
    "CURRENT_ETOR": 1776900600000,
    "OUTAGE_START": 1776864120000,
    "EST_CUSTOMERS": 1,
    "OUTAGE_CAUSE": "FOREIGN OBJ",
    "CREW_CURRENT_STATUS": "Awaiting Crew",
    "LAST_UPDATE": 1776869255000,
    "OUTAGE_START_TEXT": "2026-04-22T13:22:00Z",
    "LAST_UPDATE_TEXT": "2026-04-22T14:47:35Z",
    "CURRENT_ETOR_TEXT": "2026-04-22T23:30:00Z"
   },
   "geometry": {
    "x": -13300659.2203,
    "y": 4256792.7797000036
   }
  },
  {
   "attributes": {
    "OUTAGE_ID": "230726",
    "CURRENT_ETOR": 1776900600000,
    "OUTAGE_START": 1776864304000,
    "EST_CUSTOMERS": 1,
    "OUTAGE_CAUSE": null,
    "CREW_CURRENT_STATUS": "Awaiting T-Man",
    "LAST_UPDATE": 1776864306000,
    "OUTAGE_START_TEXT": "2026-04-22T13:25:04Z",
    "LAST_UPDATE_TEXT": "2026-04-22T13:25:06Z",
    "CURRENT_ETOR_TEXT": "2026-04-22T23:30:00Z"
   },
   "geometry": {
    "x": -13301011.4815,
    "y": 4242154.5260000005
   }
  },
  {
   "attributes": {
    "OUTAGE_ID": "230729",
    "CURRENT_ETOR": 1776879900000,
    "OUTAGE_START": 1776865022000,
    "EST_CUSTOMERS": 23,
    "OUTAGE_CAUSE": "PATROLLING",
    "CREW_CURRENT_STATUS": "T-Man On Site",
    "LAST_UPDATE": 1776870681000,
    "OUTAGE_START_TEXT": "2026-04-22T13:37:02Z",
    "LAST_UPDATE_TEXT": "2026-04-22T15:11:21Z",
    "CURRENT_ETOR_TEXT": "2026-04-22T17:45:00Z"
   },
   "geometry": {
    "x": -13582140.8391,
    "y": 4454971.6441999972
   }
  },
  {
   "attributes": {
    "OUTAGE_ID": "230733",
    "CURRENT_ETOR": 1776897000000,
    "OUTAGE_START": 1776866022000,
    "EST_CUSTOMERS": 1,
    "OUTAGE_CAUSE": "PATROLLING",
    "CREW_CURRENT_STATUS": "T-Man On Site",
    "LAST_UPDATE": 1776869470000,
    "OUTAGE_START_TEXT": "2026-04-22T13:53:42Z",
    "LAST_UPDATE_TEXT": "2026-04-22T14:51:10Z",
    "CURRENT_ETOR_TEXT": "2026-04-22T22:30:00Z"
   },
   "geometry": {
    "x": -13573946.658500001,
    "y": 4447297.1651000008
   }
  },
  {
   "attributes": {
    "OUTAGE_ID": "230735",
    "CURRENT_ETOR": 1776881700000,
    "OUTAGE_START": 1776866881000,
    "EST_CUSTOMERS": 1,
    "OUTAGE_CAUSE": null,
    "CREW_CURRENT_STATUS": "Awaiting T-Man",
    "LAST_UPDATE": 1776866887000,
    "OUTAGE_START_TEXT": "2026-04-22T14:08:01Z",
    "LAST_UPDATE_TEXT": "2026-04-22T14:08:07Z",
    "CURRENT_ETOR_TEXT": "2026-04-22T18:15:00Z"
   },
   "geometry": {
    "x": -13580863.5678,
    "y": 4447229.8162999973
   }
  },
  {
   "attributes": {
    "OUTAGE_ID": "230737",
    "CURRENT_ETOR": null,
    "OUTAGE_START": 1776866937000,
    "EST_CUSTOMERS": 1,
    "OUTAGE_CAUSE": "STORM",
    "CREW_CURRENT_STATUS": "T-Man Enroute",
    "LAST_UPDATE": 1776866941000,
    "OUTAGE_START_TEXT": "2026-04-22T14:08:57Z",
    "LAST_UPDATE_TEXT": "2026-04-22T14:09:01Z",
    "CURRENT_ETOR_TEXT": null
   },
   "geometry": {
    "x": -13412360.2268,
    "y": 4443435.3024000004
   }
  },
  {
   "attributes": {
    "OUTAGE_ID": "230738",
    "CURRENT_ETOR": null,
    "OUTAGE_START": 1776867160000,
    "EST_CUSTOMERS": 14,
    "OUTAGE_CAUSE": "STORM",
    "CREW_CURRENT_STATUS": "T-Man On Site",
    "LAST_UPDATE": 1776867462000,
    "OUTAGE_START_TEXT": "2026-04-22T14:12:40Z",
    "LAST_UPDATE_TEXT": "2026-04-22T14:17:42Z",
    "CURRENT_ETOR_TEXT": null
   },
   "geometry": {
    "x": -13497556.237199999,
    "y": 4595326.1670000032
   }
  },
  {
   "attributes": {
    "OUTAGE_ID": "230739",
    "CURRENT_ETOR": null,
    "OUTAGE_START": 1776867206000,
    "EST_CUSTOMERS": 1,
    "OUTAGE_CAUSE": "STORM",
    "CREW_CURRENT_STATUS": "Awaiting T-Man",
    "LAST_UPDATE": 1776867211000,
    "OUTAGE_START_TEXT": "2026-04-22T14:13:26Z",
    "LAST_UPDATE_TEXT": "2026-04-22T14:13:31Z",
    "CURRENT_ETOR_TEXT": null
   },
   "geometry": {
    "x": -13470744.359299999,
    "y": 4560159.0024000034
   }
  },
  {
   "attributes": {
    "OUTAGE_ID": "230740",
    "CURRENT_ETOR": null,
    "OUTAGE_START": 1776867456000,
    "EST_CUSTOMERS": 1,
    "OUTAGE_CAUSE": "STORM",
    "CREW_CURRENT_STATUS": "Awaiting T-Man",
    "LAST_UPDATE": 1776867462000,
    "OUTAGE_START_TEXT": "2026-04-22T14:17:36Z",
    "LAST_UPDATE_TEXT": "2026-04-22T14:17:42Z",
    "CURRENT_ETOR_TEXT": null
   },
   "geometry": {
    "x": -13474561.9955,
    "y": 4585771.6840000004
   }
  },
  {
   "attributes": {
    "OUTAGE_ID": "230741",
    "CURRENT_ETOR": 1776891600000,
    "OUTAGE_START": 1776867635000,
    "EST_CUSTOMERS": 1,
    "OUTAGE_CAUSE": "PATROLLING",
    "CREW_CURRENT_STATUS": "T-Man On Site",
    "LAST_UPDATE": 1776870930000,
    "OUTAGE_START_TEXT": "2026-04-22T14:20:35Z",
    "LAST_UPDATE_TEXT": "2026-04-22T15:15:30Z",
    "CURRENT_ETOR_TEXT": "2026-04-22T21:00:00Z"
   },
   "geometry": {
    "x": -13573318.406500001,
    "y": 4386652.0997999981
   }
  },
  {
   "attributes": {
    "OUTAGE_ID": "230742",
    "CURRENT_ETOR": null,
    "OUTAGE_START": 1776867646000,
    "EST_CUSTOMERS": 13,
    "OUTAGE_CAUSE": "STORM",
    "CREW_CURRENT_STATUS": "Awaiting T-Man",
    "LAST_UPDATE": 1776868310000,
    "OUTAGE_START_TEXT": "2026-04-22T14:20:46Z",
    "LAST_UPDATE_TEXT": "2026-04-22T14:31:50Z",
    "CURRENT_ETOR_TEXT": null
   },
   "geometry": {
    "x": -13476617.659699999,
    "y": 4572612.0974999964
   }
  },
  {
   "attributes": {
    "OUTAGE_ID": "230743",
    "CURRENT_ETOR": 1776904200000,
    "OUTAGE_START": 1776867920000,
    "EST_CUSTOMERS": 1,
    "OUTAGE_CAUSE": null,
    "CREW_CURRENT_STATUS": "T-Man Enroute",
    "LAST_UPDATE": 1776867923000,
    "OUTAGE_START_TEXT": "2026-04-22T14:25:20Z",
    "LAST_UPDATE_TEXT": "2026-04-22T14:25:23Z",
    "CURRENT_ETOR_TEXT": "2026-04-23T00:30:00Z"
   },
   "geometry": {
    "x": -13630590.2742,
    "y": 4661444.001000002
   }
  },
  {
   "attributes": {
    "OUTAGE_ID": "230744",
    "CURRENT_ETOR": 1776883500000,
    "OUTAGE_START": 1776867975000,
    "EST_CUSTOMERS": 1,
    "OUTAGE_CAUSE": null,
    "CREW_CURRENT_STATUS": "Awaiting T-Man",
    "LAST_UPDATE": 1776867998000,
    "OUTAGE_START_TEXT": "2026-04-22T14:26:15Z",
    "LAST_UPDATE_TEXT": "2026-04-22T14:26:38Z",
    "CURRENT_ETOR_TEXT": "2026-04-22T18:45:00Z"
   },
   "geometry": {
    "x": -13597191.6567,
    "y": 4524937.4855000004
   }
  },
  {
   "attributes": {
    "OUTAGE_ID": "230745",
    "CURRENT_ETOR": 1776883500000,
    "OUTAGE_START": 1776867931000,
    "EST_CUSTOMERS": 1,
    "OUTAGE_CAUSE": null,
    "CREW_CURRENT_STATUS": "Awaiting T-Man",
    "LAST_UPDATE": 1776867998000,
    "OUTAGE_START_TEXT": "2026-04-22T14:25:31Z",
    "LAST_UPDATE_TEXT": "2026-04-22T14:26:38Z",
    "CURRENT_ETOR_TEXT": "2026-04-22T18:45:00Z"
   },
   "geometry": {
    "x": -13597293.469599999,
    "y": 4526305.1070000008
   }
  },
  {
   "attributes": {
    "OUTAGE_ID": "230750",
    "CURRENT_ETOR": 1776884400000,
    "OUTAGE_START": 1776867780000,
    "EST_CUSTOMERS": 353,
    "OUTAGE_CAUSE": "PATROLLING",
    "CREW_CURRENT_STATUS": "T-Man On Site",
    "LAST_UPDATE": 1776871672000,
    "OUTAGE_START_TEXT": "2026-04-22T14:23:00Z",
    "LAST_UPDATE_TEXT": "2026-04-22T15:27:52Z",
    "CURRENT_ETOR_TEXT": "2026-04-22T19:00:00Z"
   },
   "geometry": {
    "x": -13328274.0217,
    "y": 4257562.6651000008
   }
  },
  {
   "attributes": {
    "OUTAGE_ID": "230751",
    "CURRENT_ETOR": 1776883500000,
    "OUTAGE_START": 1776868155000,
    "EST_CUSTOMERS": 11,
    "OUTAGE_CAUSE": "PATROLLING",
    "CREW_CURRENT_STATUS": "T-Man On Site",
    "LAST_UPDATE": 1776870219000,
    "OUTAGE_START_TEXT": "2026-04-22T14:29:15Z",
    "LAST_UPDATE_TEXT": "2026-04-22T15:03:39Z",
    "CURRENT_ETOR_TEXT": "2026-04-22T18:45:00Z"
   },
   "geometry": {
    "x": -13607119.8232,
    "y": 4507662.2056000009
   }
  },
  {
   "attributes": {
    "OUTAGE_ID": "230752",
    "CURRENT_ETOR": null,
    "OUTAGE_START": 1776868195000,
    "EST_CUSTOMERS": 1,
    "OUTAGE_CAUSE": "STORM",
    "CREW_CURRENT_STATUS": "Awaiting T-Man",
    "LAST_UPDATE": 1776868196000,
    "OUTAGE_START_TEXT": "2026-04-22T14:29:55Z",
    "LAST_UPDATE_TEXT": "2026-04-22T14:29:56Z",
    "CURRENT_ETOR_TEXT": null
   },
   "geometry": {
    "x": -13398032.079700001,
    "y": 4417146.9395999983
   }
  },
  {
   "attributes": {
    "OUTAGE_ID": "230753",
    "CURRENT_ETOR": 1776881700000,
    "OUTAGE_START": 1776868238000,
    "EST_CUSTOMERS": 1,
    "OUTAGE_CAUSE": null,
    "CREW_CURRENT_STATUS": "T-Man Enroute",
    "LAST_UPDATE": 1776868239000,
    "OUTAGE_START_TEXT": "2026-04-22T14:30:38Z",
    "LAST_UPDATE_TEXT": "2026-04-22T14:30:39Z",
    "CURRENT_ETOR_TEXT": "2026-04-22T18:15:00Z"
   },
   "geometry": {
    "x": -13596211.650800001,
    "y": 4538481.4536999986
   }
  },
  {
   "attributes": {
    "OUTAGE_ID": "230754",
    "CURRENT_ETOR": 1776898800000,
    "OUTAGE_START": 1776868200000,
    "EST_CUSTOMERS": 7,
    "OUTAGE_CAUSE": "PLNND SHUTDOWN",
    "CREW_CURRENT_STATUS": "Crew On Site",
    "LAST_UPDATE": 1776869138000,
    "OUTAGE_START_TEXT": "2026-04-22T14:30:00Z",
    "LAST_UPDATE_TEXT": "2026-04-22T14:45:38Z",
    "CURRENT_ETOR_TEXT": "2026-04-22T23:00:00Z"
   },
   "geometry": {
    "x": -13628804.877,
    "y": 4962104.1300000027
   }
  },
  {
   "attributes": {
    "OUTAGE_ID": "230755",
    "CURRENT_ETOR": null,
    "OUTAGE_START": 1776868303000,
    "EST_CUSTOMERS": 1,
    "OUTAGE_CAUSE": "STORM",
    "CREW_CURRENT_STATUS": "Awaiting T-Man",
    "LAST_UPDATE": 1776868306000,
    "OUTAGE_START_TEXT": "2026-04-22T14:31:43Z",
    "LAST_UPDATE_TEXT": "2026-04-22T14:31:46Z",
    "CURRENT_ETOR_TEXT": null
   },
   "geometry": {
    "x": -13397291.7052,
    "y": 4418431.6991000026
   }
  },
  {
   "attributes": {
    "OUTAGE_ID": "230756",
    "CURRENT_ETOR": 1776898800000,
    "OUTAGE_START": 1776868367000,
    "EST_CUSTOMERS": 1,
    "OUTAGE_CAUSE": null,
    "CREW_CURRENT_STATUS": "Awaiting T-Man",
    "LAST_UPDATE": 1776868371000,
    "OUTAGE_START_TEXT": "2026-04-22T14:32:47Z",
    "LAST_UPDATE_TEXT": "2026-04-22T14:32:51Z",
    "CURRENT_ETOR_TEXT": "2026-04-22T23:00:00Z"
   },
   "geometry": {
    "x": -13280702.0667,
    "y": 4215527.5737999976
   }
  },
  {
   "attributes": {
    "OUTAGE_ID": "230757",
    "CURRENT_ETOR": null,
    "OUTAGE_START": 1776868373000,
    "EST_CUSTOMERS": 1,
    "OUTAGE_CAUSE": "STORM",
    "CREW_CURRENT_STATUS": "T-Man On Site",
    "LAST_UPDATE": 1776868376000,
    "OUTAGE_START_TEXT": "2026-04-22T14:32:53Z",
    "LAST_UPDATE_TEXT": "2026-04-22T14:32:56Z",
    "CURRENT_ETOR_TEXT": null
   },
   "geometry": {
    "x": -13478113.0857,
    "y": 4547601.1454000026
   }
  },
  {
   "attributes": {
    "OUTAGE_ID": "230759",
    "CURRENT_ETOR": 1776905100000,
    "OUTAGE_START": 1776868680000,
    "EST_CUSTOMERS": 1,
    "OUTAGE_CAUSE": null,
    "CREW_CURRENT_STATUS": "Awaiting T-Man",
    "LAST_UPDATE": 1776868681000,
    "OUTAGE_START_TEXT": "2026-04-22T14:38:00Z",
    "LAST_UPDATE_TEXT": "2026-04-22T14:38:01Z",
    "CURRENT_ETOR_TEXT": "2026-04-23T00:45:00Z"
   },
   "geometry": {
    "x": -13567502.020500001,
    "y": 4490867.7158000022
   }
  },
  {
   "attributes": {
    "OUTAGE_ID": "230760",
    "CURRENT_ETOR": 1776905100000,
    "OUTAGE_START": 1776868685000,
    "EST_CUSTOMERS": 99,
    "OUTAGE_CAUSE": null,
    "CREW_CURRENT_STATUS": "T-Man Enroute",
    "LAST_UPDATE": 1776868686000,
    "OUTAGE_START_TEXT": "2026-04-22T14:38:05Z",
    "LAST_UPDATE_TEXT": "2026-04-22T14:38:06Z",
    "CURRENT_ETOR_TEXT": "2026-04-23T00:45:00Z"
   },
   "geometry": {
    "x": -13567338.086199999,
    "y": 4491005.8566000015
   }
  },
  {
   "attributes": {
    "OUTAGE_ID": "230761",
    "CURRENT_ETOR": 1776885300000,
    "OUTAGE_START": 1776868897000,
    "EST_CUSTOMERS": 1,
    "OUTAGE_CAUSE": null,
    "CREW_CURRENT_STATUS": "Awaiting T-Man",
    "LAST_UPDATE": 1776868901000,
    "OUTAGE_START_TEXT": "2026-04-22T14:41:37Z",
    "LAST_UPDATE_TEXT": "2026-04-22T14:41:41Z",
    "CURRENT_ETOR_TEXT": "2026-04-22T19:15:00Z"
   },
   "geometry": {
    "x": -13565937.4057,
    "y": 4481426.6468999982
   }
  },
  {
   "attributes": {
    "OUTAGE_ID": "230764",
    "CURRENT_ETOR": 1776897000000,
    "OUTAGE_START": 1776869123000,
    "EST_CUSTOMERS": 1,
    "OUTAGE_CAUSE": "PATROLLING",
    "CREW_CURRENT_STATUS": "T-Man On Site",
    "LAST_UPDATE": 1776871392000,
    "OUTAGE_START_TEXT": "2026-04-22T14:45:23Z",
    "LAST_UPDATE_TEXT": "2026-04-22T15:23:12Z",
    "CURRENT_ETOR_TEXT": "2026-04-22T22:30:00Z"
   },
   "geometry": {
    "x": -13616268.197799999,
    "y": 4560884.7317999974
   }
  },
  {
   "attributes": {
    "OUTAGE_ID": "230767",
    "CURRENT_ETOR": null,
    "OUTAGE_START": 1776869375000,
    "EST_CUSTOMERS": 6,
    "OUTAGE_CAUSE": "STORM",
    "CREW_CURRENT_STATUS": "T-Man Enroute",
    "LAST_UPDATE": 1776869433000,
    "OUTAGE_START_TEXT": "2026-04-22T14:49:35Z",
    "LAST_UPDATE_TEXT": "2026-04-22T14:50:33Z",
    "CURRENT_ETOR_TEXT": null
   },
   "geometry": {
    "x": -13531849.921799999,
    "y": 4947380.7232000008
   }
  },
  {
   "attributes": {
    "OUTAGE_ID": "230768",
    "CURRENT_ETOR": 1776881700000,
    "OUTAGE_START": 1776869495000,
    "EST_CUSTOMERS": 1,
    "OUTAGE_CAUSE": null,
    "CREW_CURRENT_STATUS": "Awaiting T-Man",
    "LAST_UPDATE": 1776869498000,
    "OUTAGE_START_TEXT": "2026-04-22T14:51:35Z",
    "LAST_UPDATE_TEXT": "2026-04-22T14:51:38Z",
    "CURRENT_ETOR_TEXT": "2026-04-22T18:15:00Z"
   },
   "geometry": {
    "x": -13610001.292100001,
    "y": 4629798.1503000036
   }
  },
  {
   "attributes": {
    "OUTAGE_ID": "230769",
    "CURRENT_ETOR": 1776901500000,
    "OUTAGE_START": 1776869541000,
    "EST_CUSTOMERS": 1,
    "OUTAGE_CAUSE": null,
    "CREW_CURRENT_STATUS": "T-Man Enroute",
    "LAST_UPDATE": 1776869542000,
    "OUTAGE_START_TEXT": "2026-04-22T14:52:21Z",
    "LAST_UPDATE_TEXT": "2026-04-22T14:52:22Z",
    "CURRENT_ETOR_TEXT": "2026-04-22T23:45:00Z"
   },
   "geometry": {
    "x": -13587620.765700001,
    "y": 4615825.8559999987
   }
  },
  {
   "attributes": {
    "OUTAGE_ID": "230770",
    "CURRENT_ETOR": null,
    "OUTAGE_START": 1776869568000,
    "EST_CUSTOMERS": 1,
    "OUTAGE_CAUSE": "STORM",
    "CREW_CURRENT_STATUS": "T-Man Enroute",
    "LAST_UPDATE": 1776869572000,
    "OUTAGE_START_TEXT": "2026-04-22T14:52:48Z",
    "LAST_UPDATE_TEXT": "2026-04-22T14:52:52Z",
    "CURRENT_ETOR_TEXT": null
   },
   "geometry": {
    "x": -13500363.963,
    "y": 4575566.6301999986
   }
  },
  {
   "attributes": {
    "OUTAGE_ID": "230771",
    "CURRENT_ETOR": null,
    "OUTAGE_START": 1776869618000,
    "EST_CUSTOMERS": 1,
    "OUTAGE_CAUSE": "STORM",
    "CREW_CURRENT_STATUS": "Awaiting T-Man",
    "LAST_UPDATE": 1776869622000,
    "OUTAGE_START_TEXT": "2026-04-22T14:53:38Z",
    "LAST_UPDATE_TEXT": "2026-04-22T14:53:42Z",
    "CURRENT_ETOR_TEXT": null
   },
   "geometry": {
    "x": -13331430.528200001,
    "y": 4410384.748999998
   }
  },
  {
   "attributes": {
    "OUTAGE_ID": "230772",
    "CURRENT_ETOR": 1776882600000,
    "OUTAGE_START": 1776869637000,
    "EST_CUSTOMERS": 1,
    "OUTAGE_CAUSE": null,
    "CREW_CURRENT_STATUS": "T-Man Enroute",
    "LAST_UPDATE": 1776869642000,
    "OUTAGE_START_TEXT": "2026-04-22T14:53:57Z",
    "LAST_UPDATE_TEXT": "2026-04-22T14:54:02Z",
    "CURRENT_ETOR_TEXT": "2026-04-22T18:30:00Z"
   },
   "geometry": {
    "x": -13580892.967599999,
    "y": 4470333.2867000028
   }
  },
  {
   "attributes": {
    "OUTAGE_ID": "230773",
    "CURRENT_ETOR": 1776898800000,
    "OUTAGE_START": 1776869788000,
    "EST_CUSTOMERS": 14,
    "OUTAGE_CAUSE": "PLNND SHUTDOWN",
    "CREW_CURRENT_STATUS": "Crew On Site",
    "LAST_UPDATE": 1776870576000,
    "OUTAGE_START_TEXT": "2026-04-22T14:56:28Z",
    "LAST_UPDATE_TEXT": "2026-04-22T15:09:36Z",
    "CURRENT_ETOR_TEXT": "2026-04-22T23:00:00Z"
   },
   "geometry": {
    "x": -13364596.3715,
    "y": 4427840.8791999966
   }
  },
  {
   "attributes": {
    "OUTAGE_ID": "230774",
    "CURRENT_ETOR": 1776902400000,
    "OUTAGE_START": 1776869859000,
    "EST_CUSTOMERS": 1,
    "OUTAGE_CAUSE": null,
    "CREW_CURRENT_STATUS": "T-Man Enroute",
    "LAST_UPDATE": 1776869861000,
    "OUTAGE_START_TEXT": "2026-04-22T14:57:39Z",
    "LAST_UPDATE_TEXT": "2026-04-22T14:57:41Z",
    "CURRENT_ETOR_TEXT": "2026-04-23T00:00:00Z"
   },
   "geometry": {
    "x": -13242638.126699999,
    "y": 4247422.1779000014
   }
  },
  {
   "attributes": {
    "OUTAGE_ID": "230775",
    "CURRENT_ETOR": null,
    "OUTAGE_START": 1776869901000,
    "EST_CUSTOMERS": 1,
    "OUTAGE_CAUSE": "STORM",
    "CREW_CURRENT_STATUS": "Awaiting T-Man",
    "LAST_UPDATE": 1776869906000,
    "OUTAGE_START_TEXT": "2026-04-22T14:58:21Z",
    "LAST_UPDATE_TEXT": "2026-04-22T14:58:26Z",
    "CURRENT_ETOR_TEXT": null
   },
   "geometry": {
    "x": -13353677.858199999,
    "y": 4375117.8752999976
   }
  },
  {
   "attributes": {
    "OUTAGE_ID": "230776",
    "CURRENT_ETOR": 1776893400000,
    "OUTAGE_START": 1776870000000,
    "EST_CUSTOMERS": 3,
    "OUTAGE_CAUSE": "PLNND SHUTDOWN",
    "CREW_CURRENT_STATUS": "Crew On Site",
    "LAST_UPDATE": 1776870308000,
    "OUTAGE_START_TEXT": "2026-04-22T15:00:00Z",
    "LAST_UPDATE_TEXT": "2026-04-22T15:05:08Z",
    "CURRENT_ETOR_TEXT": "2026-04-22T21:30:00Z"
   },
   "geometry": {
    "x": -13678723.1098,
    "y": 4661870.7207000032
   }
  },
  {
   "attributes": {
    "OUTAGE_ID": "230777",
    "CURRENT_ETOR": 1776898800000,
    "OUTAGE_START": 1776870000000,
    "EST_CUSTOMERS": 26,
    "OUTAGE_CAUSE": "PLNND SHUTDOWN",
    "CREW_CURRENT_STATUS": "Crew On Site",
    "LAST_UPDATE": 1776870318000,
    "OUTAGE_START_TEXT": "2026-04-22T15:00:00Z",
    "LAST_UPDATE_TEXT": "2026-04-22T15:05:18Z",
    "CURRENT_ETOR_TEXT": "2026-04-22T23:00:00Z"
   },
   "geometry": {
    "x": -13461652.945900001,
    "y": 4682169.2833999991
   }
  },
  {
   "attributes": {
    "OUTAGE_ID": "230778",
    "CURRENT_ETOR": 1776906900000,
    "OUTAGE_START": 1776870104000,
    "EST_CUSTOMERS": 1,
    "OUTAGE_CAUSE": null,
    "CREW_CURRENT_STATUS": "Awaiting T-Man",
    "LAST_UPDATE": 1776870106000,
    "OUTAGE_START_TEXT": "2026-04-22T15:01:44Z",
    "LAST_UPDATE_TEXT": "2026-04-22T15:01:46Z",
    "CURRENT_ETOR_TEXT": "2026-04-23T01:15:00Z"
   },
   "geometry": {
    "x": -13300716.4607,
    "y": 4250447.3176999986
   }
  },
  {
   "attributes": {
    "OUTAGE_ID": "230779",
    "CURRENT_ETOR": 1776897000000,
    "OUTAGE_START": 1776870120000,
    "EST_CUSTOMERS": 13,
    "OUTAGE_CAUSE": "STORM",
    "CREW_CURRENT_STATUS": "Awaiting T-Man",
    "LAST_UPDATE": 1776870388000,
    "OUTAGE_START_TEXT": "2026-04-22T15:02:00Z",
    "LAST_UPDATE_TEXT": "2026-04-22T15:06:28Z",
    "CURRENT_ETOR_TEXT": "2026-04-22T22:30:00Z"
   },
   "geometry": {
    "x": -13625884.583700001,
    "y": 4959490.8237999976
   }
  },
  {
   "attributes": {
    "OUTAGE_ID": "230780",
    "CURRENT_ETOR": 1776898800000,
    "OUTAGE_START": 1776870120000,
    "EST_CUSTOMERS": 2,
    "OUTAGE_CAUSE": "PLNND SHUTDOWN",
    "CREW_CURRENT_STATUS": "Crew On Site",
    "LAST_UPDATE": 1776870448000,
    "OUTAGE_START_TEXT": "2026-04-22T15:02:00Z",
    "LAST_UPDATE_TEXT": "2026-04-22T15:07:28Z",
    "CURRENT_ETOR_TEXT": "2026-04-22T23:00:00Z"
   },
   "geometry": {
    "x": -13542440.5877,
    "y": 4544193.7796000019
   }
  },
  {
   "attributes": {
    "OUTAGE_ID": "230781",
    "CURRENT_ETOR": null,
    "OUTAGE_START": 1776870307000,
    "EST_CUSTOMERS": 51,
    "OUTAGE_CAUSE": "STORM",
    "CREW_CURRENT_STATUS": "T-Man Enroute",
    "LAST_UPDATE": 1776870435000,
    "OUTAGE_START_TEXT": "2026-04-22T15:05:07Z",
    "LAST_UPDATE_TEXT": "2026-04-22T15:07:15Z",
    "CURRENT_ETOR_TEXT": null
   },
   "geometry": {
    "x": -13563731.859099999,
    "y": 4831845.0357000008
   }
  },
  {
   "attributes": {
    "OUTAGE_ID": "230782",
    "CURRENT_ETOR": 1776888000000,
    "OUTAGE_START": 1776870013000,
    "EST_CUSTOMERS": 5,
    "OUTAGE_CAUSE": "STORM",
    "CREW_CURRENT_STATUS": "Awaiting T-Man",
    "LAST_UPDATE": 1776870343000,
    "OUTAGE_START_TEXT": "2026-04-22T15:00:13Z",
    "LAST_UPDATE_TEXT": "2026-04-22T15:05:43Z",
    "CURRENT_ETOR_TEXT": "2026-04-22T20:00:00Z"
   },
   "geometry": {
    "x": -13635353.5141,
    "y": 4952806.1965000033
   }
  },
  {
   "attributes": {
    "OUTAGE_ID": "230783",
    "CURRENT_ETOR": 1776891600000,
    "OUTAGE_START": 1776870360000,
    "EST_CUSTOMERS": 1,
    "OUTAGE_CAUSE": "PLNND SHUTDOWN",
    "CREW_CURRENT_STATUS": "Crew On Site",
    "LAST_UPDATE": 1776870686000,
    "OUTAGE_START_TEXT": "2026-04-22T15:06:00Z",
    "LAST_UPDATE_TEXT": "2026-04-22T15:11:26Z",
    "CURRENT_ETOR_TEXT": "2026-04-22T21:00:00Z"
   },
   "geometry": {
    "x": -13412568.205499999,
    "y": 4174223.2945000008
   }
  },
  {
   "attributes": {
    "OUTAGE_ID": "230784",
    "CURRENT_ETOR": 1776898800000,
    "OUTAGE_START": 1776870064000,
    "EST_CUSTOMERS": 2,
    "OUTAGE_CAUSE": "STORM",
    "CREW_CURRENT_STATUS": "Awaiting T-Man",
    "LAST_UPDATE": 1776870406000,
    "OUTAGE_START_TEXT": "2026-04-22T15:01:04Z",
    "LAST_UPDATE_TEXT": "2026-04-22T15:06:46Z",
    "CURRENT_ETOR_TEXT": "2026-04-22T23:00:00Z"
   },
   "geometry": {
    "x": -13334694.3641,
    "y": 4427181.6555999964
   }
  },
  {
   "attributes": {
    "OUTAGE_ID": "230785",
    "CURRENT_ETOR": 1776884400000,
    "OUTAGE_START": 1776870240000,
    "EST_CUSTOMERS": 20,
    "OUTAGE_CAUSE": null,
    "CREW_CURRENT_STATUS": "Awaiting T-Man",
    "LAST_UPDATE": 1776870570000,
    "OUTAGE_START_TEXT": "2026-04-22T15:04:00Z",
    "LAST_UPDATE_TEXT": "2026-04-22T15:09:30Z",
    "CURRENT_ETOR_TEXT": "2026-04-22T19:00:00Z"
   },
   "geometry": {
    "x": -13608758.351599999,
    "y": 4565486.4997000024
   }
  },
  {
   "attributes": {
    "OUTAGE_ID": "230786",
    "CURRENT_ETOR": 1776884400000,
    "OUTAGE_START": 1776870078000,
    "EST_CUSTOMERS": 37,
    "OUTAGE_CAUSE": "PLNND SHUTDOWN",
    "CREW_CURRENT_STATUS": "Crew On Site",
    "LAST_UPDATE": 1776870480000,
    "OUTAGE_START_TEXT": "2026-04-22T15:01:18Z",
    "LAST_UPDATE_TEXT": "2026-04-22T15:08:00Z",
    "CURRENT_ETOR_TEXT": "2026-04-22T19:00:00Z"
   },
   "geometry": {
    "x": -13555844.886,
    "y": 4430435.7584000006
   }
  },
  {
   "attributes": {
    "OUTAGE_ID": "230787",
    "CURRENT_ETOR": 1776898800000,
    "OUTAGE_START": 1776870360000,
    "EST_CUSTOMERS": 34,
    "OUTAGE_CAUSE": "PLNND SHUTDOWN",
    "CREW_CURRENT_STATUS": "Crew On Site",
    "LAST_UPDATE": 1776870594000,
    "OUTAGE_START_TEXT": "2026-04-22T15:06:00Z",
    "LAST_UPDATE_TEXT": "2026-04-22T15:09:54Z",
    "CURRENT_ETOR_TEXT": "2026-04-22T23:00:00Z"
   },
   "geometry": {
    "x": -13461281.413800001,
    "y": 4753497.1079000011
   }
  },
  {
   "attributes": {
    "OUTAGE_ID": "230788",
    "CURRENT_ETOR": 1776898800000,
    "OUTAGE_START": 1776870133000,
    "EST_CUSTOMERS": 4,
    "OUTAGE_CAUSE": "PLNND SHUTDOWN",
    "CREW_CURRENT_STATUS": "Crew On Site",
    "LAST_UPDATE": 1776870506000,
    "OUTAGE_START_TEXT": "2026-04-22T15:02:13Z",
    "LAST_UPDATE_TEXT": "2026-04-22T15:08:26Z",
    "CURRENT_ETOR_TEXT": "2026-04-22T23:00:00Z"
   },
   "geometry": {
    "x": -13612103.922899999,
    "y": 4665616.637500003
   }
  },
  {
   "attributes": {
    "OUTAGE_ID": "230789",
    "CURRENT_ETOR": 1776889800000,
    "OUTAGE_START": 1776870130000,
    "EST_CUSTOMERS": 2,
    "OUTAGE_CAUSE": "PLNND SHUTDOWN",
    "CREW_CURRENT_STATUS": "Crew On Site",
    "LAST_UPDATE": 1776870518000,
    "OUTAGE_START_TEXT": "2026-04-22T15:02:10Z",
    "LAST_UPDATE_TEXT": "2026-04-22T15:08:38Z",
    "CURRENT_ETOR_TEXT": "2026-04-22T20:30:00Z"
   },
   "geometry": {
    "x": -13654664.5156,
    "y": 4613930.4720000029
   }
  },
  {
   "attributes": {
    "OUTAGE_ID": "230791",
    "CURRENT_ETOR": 1776898800000,
    "OUTAGE_START": 1776870208000,
    "EST_CUSTOMERS": 25,
    "OUTAGE_CAUSE": "PLNND SHUTDOWN",
    "CREW_CURRENT_STATUS": "Crew On Site",
    "LAST_UPDATE": 1776871201000,
    "OUTAGE_START_TEXT": "2026-04-22T15:03:28Z",
    "LAST_UPDATE_TEXT": "2026-04-22T15:20:01Z",
    "CURRENT_ETOR_TEXT": "2026-04-22T23:00:00Z"
   },
   "geometry": {
    "x": -13436814.172800001,
    "y": 4228045.8207999989
   }
  },
  {
   "attributes": {
    "OUTAGE_ID": "230792",
    "CURRENT_ETOR": 1776893400000,
    "OUTAGE_START": 1776870480000,
    "EST_CUSTOMERS": 6,
    "OUTAGE_CAUSE": "PLNND SHUTDOWN",
    "CREW_CURRENT_STATUS": "Crew On Site",
    "LAST_UPDATE": 1776870774000,
    "OUTAGE_START_TEXT": "2026-04-22T15:08:00Z",
    "LAST_UPDATE_TEXT": "2026-04-22T15:12:54Z",
    "CURRENT_ETOR_TEXT": "2026-04-22T21:30:00Z"
   },
   "geometry": {
    "x": -13653627.134300001,
    "y": 4613818.6098999977
   }
  },
  {
   "attributes": {
    "OUTAGE_ID": "230793",
    "CURRENT_ETOR": 1776897000000,
    "OUTAGE_START": 1776870556000,
    "EST_CUSTOMERS": 1,
    "OUTAGE_CAUSE": null,
    "CREW_CURRENT_STATUS": "Awaiting T-Man",
    "LAST_UPDATE": 1776870559000,
    "OUTAGE_START_TEXT": "2026-04-22T15:09:16Z",
    "LAST_UPDATE_TEXT": "2026-04-22T15:09:19Z",
    "CURRENT_ETOR_TEXT": "2026-04-22T22:30:00Z"
   },
   "geometry": {
    "x": -13544837.0429,
    "y": 4544831.0029999986
   }
  },
  {
   "attributes": {
    "OUTAGE_ID": "230794",
    "CURRENT_ETOR": 1776898800000,
    "OUTAGE_START": 1776870553000,
    "EST_CUSTOMERS": 2,
    "OUTAGE_CAUSE": "STORM",
    "CREW_CURRENT_STATUS": "Awaiting T-Man",
    "LAST_UPDATE": 1776870594000,
    "OUTAGE_START_TEXT": "2026-04-22T15:09:13Z",
    "LAST_UPDATE_TEXT": "2026-04-22T15:09:54Z",
    "CURRENT_ETOR_TEXT": "2026-04-22T23:00:00Z"
   },
   "geometry": {
    "x": -13634733.278099999,
    "y": 4955513.0939999968
   }
  },
  {
   "attributes": {
    "OUTAGE_ID": "230795",
    "CURRENT_ETOR": 1776898800000,
    "OUTAGE_START": 1776870288000,
    "EST_CUSTOMERS": 7,
    "OUTAGE_CAUSE": "PLNND SHUTDOWN",
    "CREW_CURRENT_STATUS": "Crew On Site",
    "LAST_UPDATE": 1776870851000,
    "OUTAGE_START_TEXT": "2026-04-22T15:04:48Z",
    "LAST_UPDATE_TEXT": "2026-04-22T15:14:11Z",
    "CURRENT_ETOR_TEXT": "2026-04-22T23:00:00Z"
   },
   "geometry": {
    "x": -13420430.789099999,
    "y": 4182912.5943000019
   }
  },
  {
   "attributes": {
    "OUTAGE_ID": "230796",
    "CURRENT_ETOR": null,
    "OUTAGE_START": 1776870625000,
    "EST_CUSTOMERS": 1,
    "OUTAGE_CAUSE": "STORM",
    "CREW_CURRENT_STATUS": "Awaiting T-Man",
    "LAST_UPDATE": 1776870627000,
    "OUTAGE_START_TEXT": "2026-04-22T15:10:25Z",
    "LAST_UPDATE_TEXT": "2026-04-22T15:10:27Z",
    "CURRENT_ETOR_TEXT": null
   },
   "geometry": {
    "x": -13421467.841699999,
    "y": 4482031.0658000037
   }
  },
  {
   "attributes": {
    "OUTAGE_ID": "230798",
    "CURRENT_ETOR": 1776887100000,
    "OUTAGE_START": 1776870759000,
    "EST_CUSTOMERS": 1,
    "OUTAGE_CAUSE": null,
    "CREW_CURRENT_STATUS": "Awaiting T-Man",
    "LAST_UPDATE": 1776870760000,
    "OUTAGE_START_TEXT": "2026-04-22T15:12:39Z",
    "LAST_UPDATE_TEXT": "2026-04-22T15:12:40Z",
    "CURRENT_ETOR_TEXT": "2026-04-22T19:45:00Z"
   },
   "geometry": {
    "x": -13702785.056699999,
    "y": 4674777.3768000007
   }
  },
  {
   "attributes": {
    "OUTAGE_ID": "230799",
    "CURRENT_ETOR": 1776883500000,
    "OUTAGE_START": 1776870757000,
    "EST_CUSTOMERS": 1,
    "OUTAGE_CAUSE": null,
    "CREW_CURRENT_STATUS": "T-Man Enroute",
    "LAST_UPDATE": 1776870761000,
    "OUTAGE_START_TEXT": "2026-04-22T15:12:37Z",
    "LAST_UPDATE_TEXT": "2026-04-22T15:12:41Z",
    "CURRENT_ETOR_TEXT": "2026-04-22T18:45:00Z"
   },
   "geometry": {
    "x": -13629840.045,
    "y": 4538320.3202000037
   }
  },
  {
   "attributes": {
    "OUTAGE_ID": "230800",
    "CURRENT_ETOR": 1776877200000,
    "OUTAGE_START": 1776870466000,
    "EST_CUSTOMERS": 17,
    "OUTAGE_CAUSE": "PLNND SHUTDOWN",
    "CREW_CURRENT_STATUS": "Crew On Site",
    "LAST_UPDATE": 1776870834000,
    "OUTAGE_START_TEXT": "2026-04-22T15:07:46Z",
    "LAST_UPDATE_TEXT": "2026-04-22T15:13:54Z",
    "CURRENT_ETOR_TEXT": "2026-04-22T17:00:00Z"
   },
   "geometry": {
    "x": -13612355.603399999,
    "y": 4510301.5732000023
   }
  },
  {
   "attributes": {
    "OUTAGE_ID": "230801",
    "CURRENT_ETOR": 1776895200000,
    "OUTAGE_START": 1776870491000,
    "EST_CUSTOMERS": 6,
    "OUTAGE_CAUSE": "PLNND SHUTDOWN",
    "CREW_CURRENT_STATUS": "Crew On Site",
    "LAST_UPDATE": 1776870870000,
    "OUTAGE_START_TEXT": "2026-04-22T15:08:11Z",
    "LAST_UPDATE_TEXT": "2026-04-22T15:14:30Z",
    "CURRENT_ETOR_TEXT": "2026-04-22T22:00:00Z"
   },
   "geometry": {
    "x": -13612247.490600001,
    "y": 4565479.2412
   }
  },
  {
   "attributes": {
    "OUTAGE_ID": "230802",
    "CURRENT_ETOR": 1776900600000,
    "OUTAGE_START": 1776871800000,
    "EST_CUSTOMERS": 1,
    "OUTAGE_CAUSE": "PLNND SHUTDOWN",
    "CREW_CURRENT_STATUS": "Crew On Site",
    "LAST_UPDATE": 1776870898000,
    "OUTAGE_START_TEXT": "2026-04-22T15:30:00Z",
    "LAST_UPDATE_TEXT": "2026-04-22T15:14:58Z",
    "CURRENT_ETOR_TEXT": "2026-04-22T23:30:00Z"
   },
   "geometry": {
    "x": -13564124.288800001,
    "y": 4432399.4611999989
   }
  },
  {
   "attributes": {
    "OUTAGE_ID": "230804",
    "CURRENT_ETOR": null,
    "OUTAGE_START": 1776870917000,
    "EST_CUSTOMERS": 1,
    "OUTAGE_CAUSE": "STORM",
    "CREW_CURRENT_STATUS": "Awaiting T-Man",
    "LAST_UPDATE": 1776870922000,
    "OUTAGE_START_TEXT": "2026-04-22T15:15:17Z",
    "LAST_UPDATE_TEXT": "2026-04-22T15:15:22Z",
    "CURRENT_ETOR_TEXT": null
   },
   "geometry": {
    "x": -13348828.445799999,
    "y": 4427227.8125
   }
  },
  {
   "attributes": {
    "OUTAGE_ID": "230805",
    "CURRENT_ETOR": null,
    "OUTAGE_START": 1776870940000,
    "EST_CUSTOMERS": 1,
    "OUTAGE_CAUSE": null,
    "CREW_CURRENT_STATUS": "Awaiting T-Man",
    "LAST_UPDATE": 1776870946000,
    "OUTAGE_START_TEXT": "2026-04-22T15:15:40Z",
    "LAST_UPDATE_TEXT": "2026-04-22T15:15:46Z",
    "CURRENT_ETOR_TEXT": null
   },
   "geometry": {
    "x": -13609240.4025,
    "y": 4563390.3056999967
   }
  },
  {
   "attributes": {
    "OUTAGE_ID": "230806",
    "CURRENT_ETOR": null,
    "OUTAGE_START": 1776871103000,
    "EST_CUSTOMERS": 1,
    "OUTAGE_CAUSE": null,
    "CREW_CURRENT_STATUS": "Awaiting T-Man",
    "LAST_UPDATE": 1776871105000,
    "OUTAGE_START_TEXT": "2026-04-22T15:18:23Z",
    "LAST_UPDATE_TEXT": "2026-04-22T15:18:25Z",
    "CURRENT_ETOR_TEXT": null
   },
   "geometry": {
    "x": -13612226.7006,
    "y": 4510313.5383000001
   }
  },
  {
   "attributes": {
    "OUTAGE_ID": "230807",
    "CURRENT_ETOR": null,
    "OUTAGE_START": 1776871132000,
    "EST_CUSTOMERS": 1,
    "OUTAGE_CAUSE": null,
    "CREW_CURRENT_STATUS": "Awaiting T-Man",
    "LAST_UPDATE": 1776871137000,
    "OUTAGE_START_TEXT": "2026-04-22T15:18:52Z",
    "LAST_UPDATE_TEXT": "2026-04-22T15:18:57Z",
    "CURRENT_ETOR_TEXT": null
   },
   "geometry": {
    "x": -13434692.43,
    "y": 4198560.4637999982
   }
  },
  {
   "attributes": {
    "OUTAGE_ID": "230808",
    "CURRENT_ETOR": 1776898800000,
    "OUTAGE_START": 1776870840000,
    "EST_CUSTOMERS": 2,
    "OUTAGE_CAUSE": "STORM",
    "CREW_CURRENT_STATUS": "Awaiting T-Man",
    "LAST_UPDATE": 1776871169000,
    "OUTAGE_START_TEXT": "2026-04-22T15:14:00Z",
    "LAST_UPDATE_TEXT": "2026-04-22T15:19:29Z",
    "CURRENT_ETOR_TEXT": "2026-04-22T23:00:00Z"
   },
   "geometry": {
    "x": -13632305.440499999,
    "y": 4954131.4008999988
   }
  },
  {
   "attributes": {
    "OUTAGE_ID": "230809",
    "CURRENT_ETOR": 1776898800000,
    "OUTAGE_START": 1776871140000,
    "EST_CUSTOMERS": 21,
    "OUTAGE_CAUSE": "PLNND SHUTDOWN",
    "CREW_CURRENT_STATUS": "Crew On Site",
    "LAST_UPDATE": 1776871426000,
    "OUTAGE_START_TEXT": "2026-04-22T15:19:00Z",
    "LAST_UPDATE_TEXT": "2026-04-22T15:23:46Z",
    "CURRENT_ETOR_TEXT": "2026-04-22T23:00:00Z"
   },
   "geometry": {
    "x": -13478771.7422,
    "y": 4238369.1018000022
   }
  },
  {
   "attributes": {
    "OUTAGE_ID": "230810",
    "CURRENT_ETOR": null,
    "OUTAGE_START": 1776871358000,
    "EST_CUSTOMERS": 1,
    "OUTAGE_CAUSE": null,
    "CREW_CURRENT_STATUS": "Awaiting T-Man",
    "LAST_UPDATE": 1776871360000,
    "OUTAGE_START_TEXT": "2026-04-22T15:22:38Z",
    "LAST_UPDATE_TEXT": "2026-04-22T15:22:40Z",
    "CURRENT_ETOR_TEXT": null
   },
   "geometry": {
    "x": -13635050.5691,
    "y": 4558800.6005000025
   }
  },
  {
   "attributes": {
    "OUTAGE_ID": "230811",
    "CURRENT_ETOR": null,
    "OUTAGE_START": 1776871367000,
    "EST_CUSTOMERS": 3,
    "OUTAGE_CAUSE": "STORM",
    "CREW_CURRENT_STATUS": "Awaiting T-Man",
    "LAST_UPDATE": 1776871391000,
    "OUTAGE_START_TEXT": "2026-04-22T15:22:47Z",
    "LAST_UPDATE_TEXT": "2026-04-22T15:23:11Z",
    "CURRENT_ETOR_TEXT": null
   },
   "geometry": {
    "x": -13283927.7302,
    "y": 4386205.7199999988
   }
  },
  {
   "attributes": {
    "OUTAGE_ID": "230812",
    "CURRENT_ETOR": null,
    "OUTAGE_START": 1776873600000,
    "EST_CUSTOMERS": 3,
    "OUTAGE_CAUSE": null,
    "CREW_CURRENT_STATUS": "Awaiting T-Man",
    "LAST_UPDATE": 1776871421000,
    "OUTAGE_START_TEXT": "2026-04-22T16:00:00Z",
    "LAST_UPDATE_TEXT": "2026-04-22T15:23:41Z",
    "CURRENT_ETOR_TEXT": null
   },
   "geometry": {
    "x": -13417851.957,
    "y": 4187452.6268000007
   }
  },
  {
   "attributes": {
    "OUTAGE_ID": "230813",
    "CURRENT_ETOR": 1776895200000,
    "OUTAGE_START": 1776871390000,
    "EST_CUSTOMERS": 77,
    "OUTAGE_CAUSE": "PLNND SHUTDOWN",
    "CREW_CURRENT_STATUS": "Awaiting T-Man",
    "LAST_UPDATE": 1776871735000,
    "OUTAGE_START_TEXT": "2026-04-22T15:23:10Z",
    "LAST_UPDATE_TEXT": "2026-04-22T15:28:55Z",
    "CURRENT_ETOR_TEXT": "2026-04-22T22:00:00Z"
   },
   "geometry": {
    "x": -13573471.4266,
    "y": 4551098.6937000006
   }
  },
  {
   "attributes": {
    "OUTAGE_ID": "230814",
    "CURRENT_ETOR": null,
    "OUTAGE_START": 1776871431000,
    "EST_CUSTOMERS": 1,
    "OUTAGE_CAUSE": null,
    "CREW_CURRENT_STATUS": "Awaiting T-Man",
    "LAST_UPDATE": 1776871432000,
    "OUTAGE_START_TEXT": "2026-04-22T15:23:51Z",
    "LAST_UPDATE_TEXT": "2026-04-22T15:23:52Z",
    "CURRENT_ETOR_TEXT": null
   },
   "geometry": {
    "x": -13433632.5557,
    "y": 4199323.7248999998
   }
  },
  {
   "attributes": {
    "OUTAGE_ID": "230815",
    "CURRENT_ETOR": null,
    "OUTAGE_START": 1776871514000,
    "EST_CUSTOMERS": 1,
    "OUTAGE_CAUSE": null,
    "CREW_CURRENT_STATUS": "Awaiting T-Man",
    "LAST_UPDATE": 1776871516000,
    "OUTAGE_START_TEXT": "2026-04-22T15:25:14Z",
    "LAST_UPDATE_TEXT": "2026-04-22T15:25:16Z",
    "CURRENT_ETOR_TEXT": null
   },
   "geometry": {
    "x": -13498246.562199999,
    "y": 4345496.9145999998
   }
  },
  {
   "attributes": {
    "OUTAGE_ID": "230816",
    "CURRENT_ETOR": null,
    "OUTAGE_START": 1776871516000,
    "EST_CUSTOMERS": 32,
    "OUTAGE_CAUSE": null,
    "CREW_CURRENT_STATUS": "T-Man Enroute",
    "LAST_UPDATE": 1776871536000,
    "OUTAGE_START_TEXT": "2026-04-22T15:25:16Z",
    "LAST_UPDATE_TEXT": "2026-04-22T15:25:36Z",
    "CURRENT_ETOR_TEXT": null
   },
   "geometry": {
    "x": -13604121.3057,
    "y": 4549348.1926999986
   }
  },
  {
   "attributes": {
    "OUTAGE_ID": "230817",
    "CURRENT_ETOR": null,
    "OUTAGE_START": 1776871576000,
    "EST_CUSTOMERS": 1,
    "OUTAGE_CAUSE": "STORM",
    "CREW_CURRENT_STATUS": "Awaiting T-Man",
    "LAST_UPDATE": 1776871580000,
    "OUTAGE_START_TEXT": "2026-04-22T15:26:16Z",
    "LAST_UPDATE_TEXT": "2026-04-22T15:26:20Z",
    "CURRENT_ETOR_TEXT": null
   },
   "geometry": {
    "x": -13532897.866599999,
    "y": 4944185.6332999989
   }
  },
  {
   "attributes": {
    "OUTAGE_ID": "230818",
    "CURRENT_ETOR": null,
    "OUTAGE_START": 1776871582000,
    "EST_CUSTOMERS": 1,
    "OUTAGE_CAUSE": "STORM",
    "CREW_CURRENT_STATUS": "T-Man On Site",
    "LAST_UPDATE": 1776871586000,
    "OUTAGE_START_TEXT": "2026-04-22T15:26:22Z",
    "LAST_UPDATE_TEXT": "2026-04-22T15:26:26Z",
    "CURRENT_ETOR_TEXT": null
   },
   "geometry": {
    "x": -13324203.6853,
    "y": 4420266.1058000028
   }
  },
  {
   "attributes": {
    "OUTAGE_ID": "230819",
    "CURRENT_ETOR": 1776898800000,
    "OUTAGE_START": 1776871620000,
    "EST_CUSTOMERS": 2,
    "OUTAGE_CAUSE": "PLNND SHUTDOWN",
    "CREW_CURRENT_STATUS": "Crew On Site",
    "LAST_UPDATE": 1776871725000,
    "OUTAGE_START_TEXT": "2026-04-22T15:27:00Z",
    "LAST_UPDATE_TEXT": "2026-04-22T15:28:45Z",
    "CURRENT_ETOR_TEXT": "2026-04-22T23:00:00Z"
   },
   "geometry": {
    "x": -13606954.601500001,
    "y": 4663348.007600002
   }
  },
  {
   "attributes": {
    "OUTAGE_ID": "230820",
    "CURRENT_ETOR": null,
    "OUTAGE_START": 1776871652000,
    "EST_CUSTOMERS": 1,
    "OUTAGE_CAUSE": "STORM",
    "CREW_CURRENT_STATUS": "Awaiting T-Man",
    "LAST_UPDATE": 1776871656000,
    "OUTAGE_START_TEXT": "2026-04-22T15:27:32Z",
    "LAST_UPDATE_TEXT": "2026-04-22T15:27:36Z",
    "CURRENT_ETOR_TEXT": null
   },
   "geometry": {
    "x": -13367825.835200001,
    "y": 4276565.9233999997
   }
  }
 ]
}