{
 "displayFieldName": "OUTAGE_ID",
 "fieldAliases": {
  "OUTAGE_ID": "OUTAGE_ID",
  "CURRENT_ETOR": "Estimated Restoration",
  "OUTAGE_START": "Start Time",
  "EST_CUSTOMERS": "Customers Affected",
  "OUTAGE_CAUSE": "Cause",
  "CREW_CURRENT_STATUS": "Status",
  "LAST_UPDATE": "Last Updated",
  "OUTAGE_START_TEXT": "OUTAGE_START_TEXT",
  "LAST_UPDATE_TEXT": "LAST_UPDATE_TEXT",
  "CURRENT_ETOR_TEXT": "CURRENT_ETOR_TEXT"
 },
 "geometryType": "esriGeometryPoint",
 "spatialReference": {
  "wkid": 102100,
  "latestWkid": 3857
 },
 "fields": [
  {
   "name": "OUTAGE_ID",
   "type": "esriFieldTypeString",
   "alias": "OUTAGE_ID",
   "length": 255
  },
  {
   "name": "CURRENT_ETOR",
   "type": "esriFieldTypeDate",
   "alias": "Estimated Restoration",
   "length": 8
  },
  {
   "name": "OUTAGE_START",
   "type": "esriFieldTypeDate",
   "alias": "Start Time",
   "length": 8
  },
  {
   "name": "EST_CUSTOMERS",
   "type": "esriFieldTypeInteger",
   "alias": "Customers Affected"
  },
  {
   "name": "OUTAGE_CAUSE",
   "type": "esriFieldTypeString",
   "alias": "Cause",
   "length": 255
  },
  {
   "name": "CREW_CURRENT_STATUS",
   "type": "esriFieldTypeString",
   "alias": "Status",
   "length": 255
  },
  {
   "name": "LAST_UPDATE",
   "type": "esriFieldTypeDate",
   "alias": "Last Updated",
   "length": 8
  },
  {
   "name": "OUTAGE_START_TEXT",
   "type": "esriFieldTypeString",
   "alias": "OUTAGE_START_TEXT",
   "length": 255
  },
  {
   "name": "LAST_UPDATE_TEXT",
   "type": "esriFieldTypeString",
   "alias": "LAST_UPDATE_TEXT",
   "length": 255
  },
  {
   "name": "CURRENT_ETOR_TEXT",
   "type": "esriFieldTypeString",
   "alias": "CURRENT_ETOR_TEXT",
   "length": 255
  }
 ],
 "features": [
  {
   "attributes": {
    "OUTAGE_ID": "238953",
    "CURRENT_ETOR": 1777867200000,
    "OUTAGE_START": 1777820746000,
    "EST_CUSTOMERS": 22,
    "OUTAGE_CAUSE": "BRKN UG EQUIPMNT",
    "CREW_CURRENT_STATUS": "Crew On Site",
    "LAST_UPDATE": 1777852905000,
    "OUTAGE_START_TEXT": "2026-05-03T15:05:46Z",
    "LAST_UPDATE_TEXT": "2026-05-04T00:01:45Z",
    "CURRENT_ETOR_TEXT": "2026-05-04T04:00:00Z"
   },
   "geometry": {
    "x": -13570815.1908,
    "y": 4374835.7093999982
   }
  },
  {
   "attributes": {
    "OUTAGE_ID": "239179",
    "CURRENT_ETOR": 1777867200000,
    "OUTAGE_START": 1777853760000,
    "EST_CUSTOMERS": 4401,
    "OUTAGE_CAUSE": "EMERG REPAIRS",
    "CREW_CURRENT_STATUS": "Crew On Site",
    "LAST_UPDATE": 1777863089000,
    "OUTAGE_START_TEXT": "2026-05-04T00:16:00Z",
    "LAST_UPDATE_TEXT": "2026-05-04T02:51:29Z",
    "CURRENT_ETOR_TEXT": "2026-05-04T04:00:00Z"
   },
   "geometry": {
    "x": -13686484.0701,
    "y": 4635201.5976999998
   }
  },
  {
   "attributes": {
    "OUTAGE_ID": "239197",
    "CURRENT_ETOR": 1777872600000,
    "OUTAGE_START": 1777859118000,
    "EST_CUSTOMERS": 2,
    "OUTAGE_CAUSE": "PATROLLING",
    "CREW_CURRENT_STATUS": "Awaiting Crew",
    "LAST_UPDATE": 1777862408000,
    "OUTAGE_START_TEXT": "2026-05-04T01:45:18Z",
    "LAST_UPDATE_TEXT": "2026-05-04T02:40:08Z",
    "CURRENT_ETOR_TEXT": "2026-05-04T05:30:00Z"
   },
   "geometry": {
    "x": -13386813.103799999,
    "y": 4453970.2559999973
   }
  },
  {
   "attributes": {
    "OUTAGE_ID": "238995",
    "CURRENT_ETOR": 1777892400000,
    "OUTAGE_START": 1777826247000,
    "EST_CUSTOMERS": 14,
    "OUTAGE_CAUSE": "EMERG REPAIRS",
    "CREW_CURRENT_STATUS": "Crew On Site",
    "LAST_UPDATE": 1777846127000,
    "OUTAGE_START_TEXT": "2026-05-03T16:37:27Z",
    "LAST_UPDATE_TEXT": "2026-05-03T22:08:47Z",
    "CURRENT_ETOR_TEXT": "2026-05-04T11:00:00Z"
   },
   "geometry": {
    "x": -13336282.8255,
    "y": 4407973.1623999998
   }
  },
  {
   "attributes": {
    "OUTAGE_ID": "239121",
    "CURRENT_ETOR": 1777872600000,
    "OUTAGE_START": 1777849207000,
    "EST_CUSTOMERS": 2,
    "OUTAGE_CAUSE": "DAMGE UG CABLE",
    "CREW_CURRENT_STATUS": "Crew On Site",
    "LAST_UPDATE": 1777859080000,
    "OUTAGE_START_TEXT": "2026-05-03T23:00:07Z",
    "LAST_UPDATE_TEXT": "2026-05-04T01:44:40Z",
    "CURRENT_ETOR_TEXT": "2026-05-04T05:30:00Z"
   },
   "geometry": {
    "x": -13606498.275600001,
    "y": 4894470.9742000028
   }
  },
  {
   "attributes": {
    "OUTAGE_ID": "239209",
    "CURRENT_ETOR": 1777885200000,
    "OUTAGE_START": 1777861069000,
    "EST_CUSTOMERS": 1,
    "OUTAGE_CAUSE": null,
    "CREW_CURRENT_STATUS": "T-Man Enroute",
    "LAST_UPDATE": 1777861073000,
    "OUTAGE_START_TEXT": "2026-05-04T02:17:49Z",
    "LAST_UPDATE_TEXT": "2026-05-04T02:17:53Z",
    "CURRENT_ETOR_TEXT": "2026-05-04T09:00:00Z"
   },
   "geometry": {
    "x": -13239614.436700001,
    "y": 4217301.7453999966
   }
  },
  {
   "attributes": {
    "OUTAGE_ID": "239223",
    "CURRENT_ETOR": 1777893300000,
    "OUTAGE_START": 1777862051000,
    "EST_CUSTOMERS": 1,
    "OUTAGE_CAUSE": null,
    "CREW_CURRENT_STATUS": "T-Man Enroute",
    "LAST_UPDATE": 1777862053000,
    "OUTAGE_START_TEXT": "2026-05-04T02:34:11Z",
    "LAST_UPDATE_TEXT": "2026-05-04T02:34:13Z",
    "CURRENT_ETOR_TEXT": "2026-05-04T11:15:00Z"
   },
   "geometry": {
    "x": -13583102.2096,
    "y": 4449089.0333999991
   }
  },
  {
   "attributes": {
    "OUTAGE_ID": "239133",
    "CURRENT_ETOR": 1777874400000,
    "OUTAGE_START": 1777850700000,
    "EST_CUSTOMERS": 37,
    "OUTAGE_CAUSE": "REPLCE TXFMR",
    "CREW_CURRENT_STATUS": "Awaiting Crew",
    "LAST_UPDATE": 1777862905000,
    "OUTAGE_START_TEXT": "2026-05-03T23:25:00Z",
    "LAST_UPDATE_TEXT": "2026-05-04T02:48:25Z",
    "CURRENT_ETOR_TEXT": "2026-05-04T06:00:00Z"
   },
   "geometry": {
    "x": -13253759.1107,
    "y": 4204743.7062000036
   }
  },
  {
   "attributes": {
    "OUTAGE_ID": "239231",
    "CURRENT_ETOR": null,
    "OUTAGE_START": 1777863087000,
    "EST_CUSTOMERS": 1,
    "OUTAGE_CAUSE": null,
    "CREW_CURRENT_STATUS": "Awaiting T-Man",
    "LAST_UPDATE": 1777863092000,
    "OUTAGE_START_TEXT": "2026-05-04T02:51:27Z",
    "LAST_UPDATE_TEXT": "2026-05-04T02:51:32Z",
    "CURRENT_ETOR_TEXT": null
   },
   "geometry": {
    "x": -13592215.804200001,
    "y": 4578611.9654999971
   }
  },
  {
   "attributes": {
    "OUTAGE_ID": "239153",
    "CURRENT_ETOR": 1777875300000,
    "OUTAGE_START": 1777851480000,
    "EST_CUSTOMERS": 5,
    "OUTAGE_CAUSE": "TREE CONTACT",
    "CREW_CURRENT_STATUS": "Awaiting Crew",
    "LAST_UPDATE": 1777860905000,
    "OUTAGE_START_TEXT": "2026-05-03T23:38:00Z",
    "LAST_UPDATE_TEXT": "2026-05-04T02:15:05Z",
    "CURRENT_ETOR_TEXT": "2026-05-04T06:15:00Z"
   },
   "geometry": {
    "x": -13573634.3344,
    "y": 4457287.2964000031
   }
  },
  {
   "attributes": {
    "OUTAGE_ID": "239177",
    "CURRENT_ETOR": 1777869000000,
    "OUTAGE_START": 1777853795000,
    "EST_CUSTOMERS": 1,
    "OUTAGE_CAUSE": "PATROLLING",
    "CREW_CURRENT_STATUS": "T-Man On Site",
    "LAST_UPDATE": 1777858699000,
    "OUTAGE_START_TEXT": "2026-05-04T00:16:35Z",
    "LAST_UPDATE_TEXT": "2026-05-04T01:38:19Z",
    "CURRENT_ETOR_TEXT": "2026-05-04T04:30:00Z"
   },
   "geometry": {
    "x": -13455493.2063,
    "y": 4261962.3958000019
   }
  },
  {
   "attributes": {
    "OUTAGE_ID": "239195",
    "CURRENT_ETOR": 1777892400000,
    "OUTAGE_START": 1777858094000,
    "EST_CUSTOMERS": 1,
    "OUTAGE_CAUSE": null,
    "CREW_CURRENT_STATUS": "Awaiting T-Man",
    "LAST_UPDATE": 1777858095000,
    "OUTAGE_START_TEXT": "2026-05-04T01:28:14Z",
    "LAST_UPDATE_TEXT": "2026-05-04T01:28:15Z",
    "CURRENT_ETOR_TEXT": "2026-05-04T11:00:00Z"
   },
   "geometry": {
    "x": -13508368.990699999,
    "y": 4584430.8150999993
   }
  },
  {
   "attributes": {
    "OUTAGE_ID": "239217",
    "CURRENT_ETOR": 1777883400000,
    "OUTAGE_START": 1777861680000,
    "EST_CUSTOMERS": 1,
    "OUTAGE_CAUSE": null,
    "CREW_CURRENT_STATUS": "Awaiting T-Man",
    "LAST_UPDATE": 1777861682000,
    "OUTAGE_START_TEXT": "2026-05-04T02:28:00Z",
    "LAST_UPDATE_TEXT": "2026-05-04T02:28:02Z",
    "CURRENT_ETOR_TEXT": "2026-05-04T08:30:00Z"
   },
   "geometry": {
    "x": -13240014.567600001,
    "y": 4205297.746100001
   }
  },
  {
   "attributes": {
    "OUTAGE_ID": "239230",
    "CURRENT_ETOR": null,
    "OUTAGE_START": 1777863064000,
    "EST_CUSTOMERS": 1,
    "OUTAGE_CAUSE": null,
    "CREW_CURRENT_STATUS": "Awaiting T-Man",
    "LAST_UPDATE": 1777863067000,
    "OUTAGE_START_TEXT": "2026-05-04T02:51:04Z",
    "LAST_UPDATE_TEXT": "2026-05-04T02:51:07Z",
    "CURRENT_ETOR_TEXT": null
   },
   "geometry": {
    "x": -13468047.672600001,
    "y": 4730417.8672999963
   }
  },
  {
   "attributes": {
    "OUTAGE_ID": "239193",
    "CURRENT_ETOR": 1777871700000,
    "OUTAGE_START": 1777857810000,
    "EST_CUSTOMERS": 32,
    "OUTAGE_CAUSE": "EMERG REPAIRS",
    "CREW_CURRENT_STATUS": "Crew On Site",
    "LAST_UPDATE": 1777861340000,
    "OUTAGE_START_TEXT": "2026-05-04T01:23:30Z",
    "LAST_UPDATE_TEXT": "2026-05-04T02:22:20Z",
    "CURRENT_ETOR_TEXT": "2026-05-04T05:15:00Z"
   },
   "geometry": {
    "x": -13593841.7147,
    "y": 4534139.2507999986
   }
  },
  {
   "attributes": {
    "OUTAGE_ID": "239218",
    "CURRENT_ETOR": 1777883400000,
    "OUTAGE_START": 1777861688000,
    "EST_CUSTOMERS": 1,
    "OUTAGE_CAUSE": null,
    "CREW_CURRENT_STATUS": "T-Man Enroute",
    "LAST_UPDATE": 1777861690000,
    "OUTAGE_START_TEXT": "2026-05-04T02:28:08Z",
    "LAST_UPDATE_TEXT": "2026-05-04T02:28:10Z",
    "CURRENT_ETOR_TEXT": "2026-05-04T08:30:00Z"
   },
   "geometry": {
    "x": -13528860.439300001,
    "y": 4662054.7303000018
   }
  },
  {
   "attributes": {
    "OUTAGE_ID": "239227",
    "CURRENT_ETOR": null,
    "OUTAGE_START": 1777862682000,
    "EST_CUSTOMERS": 1,
    "OUTAGE_CAUSE": null,
    "CREW_CURRENT_STATUS": "Awaiting T-Man",
    "LAST_UPDATE": 1777862685000,
    "OUTAGE_START_TEXT": "2026-05-04T02:44:42Z",
    "LAST_UPDATE_TEXT": "2026-05-04T02:44:45Z",
    "CURRENT_ETOR_TEXT": null
   },
   "geometry": {
    "x": -13591616.658599999,
    "y": 4580893.5073999986
   }
  },
  {
   "attributes": {
    "OUTAGE_ID": "239073",
    "CURRENT_ETOR": 1777864500000,
    "OUTAGE_START": 1777840617000,
    "EST_CUSTOMERS": 15,
    "OUTAGE_CAUSE": "PATROLLING",
    "CREW_CURRENT_STATUS": "Awaiting T-Man",
    "LAST_UPDATE": 1777862257000,
    "OUTAGE_START_TEXT": "2026-05-03T20:36:57Z",
    "LAST_UPDATE_TEXT": "2026-05-04T02:37:37Z",
    "CURRENT_ETOR_TEXT": "2026-05-04T03:15:00Z"
   },
   "geometry": {
    "x": -13543508.884199999,
    "y": 4397396.4069000036
   }
  },
  {
   "attributes": {
    "OUTAGE_ID": "239083",
    "CURRENT_ETOR": 1777887000000,
    "OUTAGE_START": 1777842289000,
    "EST_CUSTOMERS": 1,
    "OUTAGE_CAUSE": "EMERG REPAIRS",
    "CREW_CURRENT_STATUS": "Crew On Site",
    "LAST_UPDATE": 1777857538000,
    "OUTAGE_START_TEXT": "2026-05-03T21:04:49Z",
    "LAST_UPDATE_TEXT": "2026-05-04T01:18:58Z",
    "CURRENT_ETOR_TEXT": "2026-05-04T09:30:00Z"
   },
   "geometry": {
    "x": -13368469.523800001,
    "y": 4435173.503700003
   }
  },
  {
   "attributes": {
    "OUTAGE_ID": "239091",
    "CURRENT_ETOR": 1777875780000,
    "OUTAGE_START": 1777843260000,
    "EST_CUSTOMERS": 29,
    "OUTAGE_CAUSE": "LGHTNING",
    "CREW_CURRENT_STATUS": "Awaiting Crew",
    "LAST_UPDATE": 1777854277000,
    "OUTAGE_START_TEXT": "2026-05-03T21:21:00Z",
    "LAST_UPDATE_TEXT": "2026-05-04T00:24:37Z",
    "CURRENT_ETOR_TEXT": "2026-05-04T06:23:00Z"
   },
   "geometry": {
    "x": -13814890.1535,
    "y": 4945576.7951000035
   }
  },
  {
   "attributes": {
    "OUTAGE_ID": "239192",
    "CURRENT_ETOR": 1777870800000,
    "OUTAGE_START": 1777857030000,
    "EST_CUSTOMERS": 842,
    "OUTAGE_CAUSE": "PATROLLING",
    "CREW_CURRENT_STATUS": "T-Man On Site",
    "LAST_UPDATE": 1777861570000,
    "OUTAGE_START_TEXT": "2026-05-04T01:10:30Z",
    "LAST_UPDATE_TEXT": "2026-05-04T02:26:10Z",
    "CURRENT_ETOR_TEXT": "2026-05-04T05:00:00Z"
   },
   "geometry": {
    "x": -13588969.7358,
    "y": 4528431.7749999985
   }
  },
  {
   "attributes": {
    "OUTAGE_ID": "239198",
    "CURRENT_ETOR": 1777877100000,
    "OUTAGE_START": 1777859373000,
    "EST_CUSTOMERS": 91,
    "OUTAGE_CAUSE": null,
    "CREW_CURRENT_STATUS": "T-Man Enroute",
    "LAST_UPDATE": 1777859651000,
    "OUTAGE_START_TEXT": "2026-05-04T01:49:33Z",
    "LAST_UPDATE_TEXT": "2026-05-04T01:54:11Z",
    "CURRENT_ETOR_TEXT": "2026-05-04T06:45:00Z"
   },
   "geometry": {
    "x": -13256018.483100001,
    "y": 4210813.4355000034
   }
  },
  {
   "attributes": {
    "OUTAGE_ID": "239200",
    "CURRENT_ETOR": 1777878000000,
    "OUTAGE_START": 1777859715000,
    "EST_CUSTOMERS": 1,
    "OUTAGE_CAUSE": null,
    "CREW_CURRENT_STATUS": "T-Man Enroute",
    "LAST_UPDATE": 1777859721000,
    "OUTAGE_START_TEXT": "2026-05-04T01:55:15Z",
    "LAST_UPDATE_TEXT": "2026-05-04T01:55:21Z",
    "CURRENT_ETOR_TEXT": "2026-05-04T07:00:00Z"
   },
   "geometry": {
    "x": -13542237.280099999,
    "y": 4401925.5806000009
   }
  },
  {
   "attributes": {
    "OUTAGE_ID": "239211",
    "CURRENT_ETOR": 1777881600000,
    "OUTAGE_START": 1777861097000,
    "EST_CUSTOMERS": 40,
    "OUTAGE_CAUSE": null,
    "CREW_CURRENT_STATUS": "Awaiting T-Man",
    "LAST_UPDATE": 1777862066000,
    "OUTAGE_START_TEXT": "2026-05-04T02:18:17Z",
    "LAST_UPDATE_TEXT": "2026-05-04T02:34:26Z",
    "CURRENT_ETOR_TEXT": "2026-05-04T08:00:00Z"
   },
   "geometry": {
    "x": -13570653.769099999,
    "y": 4374751.755400002
   }
  },
  {
   "attributes": {
    "OUTAGE_ID": "239216",
    "CURRENT_ETOR": 1777878900000,
    "OUTAGE_START": 1777861613000,
    "EST_CUSTOMERS": 1,
    "OUTAGE_CAUSE": null,
    "CREW_CURRENT_STATUS": "T-Man Enroute",
    "LAST_UPDATE": 1777862479000,
    "OUTAGE_START_TEXT": "2026-05-04T02:26:53Z",
    "LAST_UPDATE_TEXT": "2026-05-04T02:41:19Z",
    "CURRENT_ETOR_TEXT": "2026-05-04T07:15:00Z"
   },
   "geometry": {
    "x": -13288534.2892,
    "y": 4277821.2040999979
   }
  },
  {
   "attributes": {
    "OUTAGE_ID": "239229",
    "CURRENT_ETOR": null,
    "OUTAGE_START": 1777862899000,
    "EST_CUSTOMERS": 1,
    "OUTAGE_CAUSE": null,
    "CREW_CURRENT_STATUS": "Awaiting T-Man",
    "LAST_UPDATE": 1777862900000,
    "OUTAGE_START_TEXT": "2026-05-04T02:48:19Z",
    "LAST_UPDATE_TEXT": "2026-05-04T02:48:20Z",
    "CURRENT_ETOR_TEXT": null
   },
   "geometry": {
    "x": -13591678.5757,
    "y": 4578340.3068000004
   }
  },
  {
   "attributes": {
    "OUTAGE_ID": "238957",
    "CURRENT_ETOR": 1777863600000,
    "OUTAGE_START": 1777821537000,
    "EST_CUSTOMERS": 10,
    "OUTAGE_CAUSE": "THRD PARTY",
    "CREW_CURRENT_STATUS": "Crew On Site",
    "LAST_UPDATE": 1777837097000,
    "OUTAGE_START_TEXT": "2026-05-03T15:18:57Z",
    "LAST_UPDATE_TEXT": "2026-05-03T19:38:17Z",
    "CURRENT_ETOR_TEXT": "2026-05-04T03:00:00Z"
   },
   "geometry": {
    "x": -13543207.1239,
    "y": 4450026.8887000009
   }
  },
  {
   "attributes": {
    "OUTAGE_ID": "239084",
    "CURRENT_ETOR": 1777878900000,
    "OUTAGE_START": 1777842300000,
    "EST_CUSTOMERS": 25,
    "OUTAGE_CAUSE": "EMERG REPAIRS",
    "CREW_CURRENT_STATUS": "Crew On Site",
    "LAST_UPDATE": 1777862050000,
    "OUTAGE_START_TEXT": "2026-05-03T21:05:00Z",
    "LAST_UPDATE_TEXT": "2026-05-04T02:34:10Z",
    "CURRENT_ETOR_TEXT": "2026-05-04T07:15:00Z"
   },
   "geometry": {
    "x": -13332019.9495,
    "y": 4382855.4780000001
   }
  },
  {
   "attributes": {
    "OUTAGE_ID": "239113",
    "CURRENT_ETOR": 1777878000000,
    "OUTAGE_START": 1777847097000,
    "EST_CUSTOMERS": 2,
    "OUTAGE_CAUSE": "REPLCE TXFMR",
    "CREW_CURRENT_STATUS": "Awaiting Crew",
    "LAST_UPDATE": 1777856407000,
    "OUTAGE_START_TEXT": "2026-05-03T22:24:57Z",
    "LAST_UPDATE_TEXT": "2026-05-04T01:00:07Z",
    "CURRENT_ETOR_TEXT": "2026-05-04T07:00:00Z"
   },
   "geometry": {
    "x": -13574696.755199999,
    "y": 4806089.1230999976
   }
  },
  {
   "attributes": {
    "OUTAGE_ID": "239134",
    "CURRENT_ETOR": 1777872600000,
    "OUTAGE_START": 1777851100000,
    "EST_CUSTOMERS": 12,
    "OUTAGE_CAUSE": "EMERG REPAIRS",
    "CREW_CURRENT_STATUS": "Crew On Site",
    "LAST_UPDATE": 1777858934000,
    "OUTAGE_START_TEXT": "2026-05-03T23:31:40Z",
    "LAST_UPDATE_TEXT": "2026-05-04T01:42:14Z",
    "CURRENT_ETOR_TEXT": "2026-05-04T05:30:00Z"
   },
   "geometry": {
    "x": -13585051.9769,
    "y": 4524813
   }
  },
  {
   "attributes": {
    "OUTAGE_ID": "239181",
    "CURRENT_ETOR": 1777869000000,
    "OUTAGE_START": 1777854319000,
    "EST_CUSTOMERS": 1,
    "OUTAGE_CAUSE": "REPLCE TXFMR",
    "CREW_CURRENT_STATUS": "Awaiting Crew",
    "LAST_UPDATE": 1777861210000,
    "OUTAGE_START_TEXT": "2026-05-04T00:25:19Z",
    "LAST_UPDATE_TEXT": "2026-05-04T02:20:10Z",
    "CURRENT_ETOR_TEXT": "2026-05-04T04:30:00Z"
   },
   "geometry": {
    "x": -13490567.166299999,
    "y": 4683827.2277000025
   }
  },
  {
   "attributes": {
    "OUTAGE_ID": "239182",
    "CURRENT_ETOR": 1777890600000,
    "OUTAGE_START": 1777854625000,
    "EST_CUSTOMERS": 1,
    "OUTAGE_CAUSE": null,
    "CREW_CURRENT_STATUS": "Awaiting T-Man",
    "LAST_UPDATE": 1777862688000,
    "OUTAGE_START_TEXT": "2026-05-04T00:30:25Z",
    "LAST_UPDATE_TEXT": "2026-05-04T02:44:48Z",
    "CURRENT_ETOR_TEXT": "2026-05-04T10:30:00Z"
   },
   "geometry": {
    "x": -13697608.407099999,
    "y": 4626534.1489999965
   }
  },
  {
   "attributes": {
    "OUTAGE_ID": "239191",
    "CURRENT_ETOR": 1777869000000,
    "OUTAGE_START": 1777855954000,
    "EST_CUSTOMERS": 12,
    "OUTAGE_CAUSE": "EMERG REPAIRS",
    "CREW_CURRENT_STATUS": "Awaiting Crew",
    "LAST_UPDATE": 1777860360000,
    "OUTAGE_START_TEXT": "2026-05-04T00:52:34Z",
    "LAST_UPDATE_TEXT": "2026-05-04T02:06:00Z",
    "CURRENT_ETOR_TEXT": "2026-05-04T04:30:00Z"
   },
   "geometry": {
    "x": -13536427.605799999,
    "y": 4433471.934299998
   }
  },
  {
   "attributes": {
    "OUTAGE_ID": "239212",
    "CURRENT_ETOR": 1777879800000,
    "OUTAGE_START": 1777861178000,
    "EST_CUSTOMERS": 1,
    "OUTAGE_CAUSE": "PATROLLING",
    "CREW_CURRENT_STATUS": "T-Man On Site",
    "LAST_UPDATE": 1777862835000,
    "OUTAGE_START_TEXT": "2026-05-04T02:19:38Z",
    "LAST_UPDATE_TEXT": "2026-05-04T02:47:15Z",
    "CURRENT_ETOR_TEXT": "2026-05-04T07:30:00Z"
   },
   "geometry": {
    "x": -13609910.9836,
    "y": 4508620.3959000036
   }
  },
  {
   "attributes": {
    "OUTAGE_ID": "239214",
    "CURRENT_ETOR": 1777877100000,
    "OUTAGE_START": 1777861415000,
    "EST_CUSTOMERS": 1,
    "OUTAGE_CAUSE": null,
    "CREW_CURRENT_STATUS": "Awaiting T-Man",
    "LAST_UPDATE": 1777861416000,
    "OUTAGE_START_TEXT": "2026-05-04T02:23:35Z",
    "LAST_UPDATE_TEXT": "2026-05-04T02:23:36Z",
    "CURRENT_ETOR_TEXT": "2026-05-04T06:45:00Z"
   },
   "geometry": {
    "x": -13663134.3113,
    "y": 4643042.9421000034
   }
  },
  {
   "attributes": {
    "OUTAGE_ID": "239215",
    "CURRENT_ETOR": 1777889700000,
    "OUTAGE_START": 1777861565000,
    "EST_CUSTOMERS": 1,
    "OUTAGE_CAUSE": null,
    "CREW_CURRENT_STATUS": "Awaiting T-Man",
    "LAST_UPDATE": 1777861570000,
    "OUTAGE_START_TEXT": "2026-05-04T02:26:05Z",
    "LAST_UPDATE_TEXT": "2026-05-04T02:26:10Z",
    "CURRENT_ETOR_TEXT": "2026-05-04T10:15:00Z"
   },
   "geometry": {
    "x": -13627182.707,
    "y": 4550641.6335000023
   }
  },
  {
   "attributes": {
    "OUTAGE_ID": "239228",
    "CURRENT_ETOR": null,
    "OUTAGE_START": 1777862705000,
    "EST_CUSTOMERS": 9,
    "OUTAGE_CAUSE": null,
    "CREW_CURRENT_STATUS": "T-Man Enroute",
    "LAST_UPDATE": 1777862710000,
    "OUTAGE_START_TEXT": "2026-05-04T02:45:05Z",
    "LAST_UPDATE_TEXT": "2026-05-04T02:45:10Z",
    "CURRENT_ETOR_TEXT": null
   },
   "geometry": {
    "x": -13591797.446899999,
    "y": 4580532.6577000022
   }
  },
  {
   "attributes": {
    "OUTAGE_ID": "239032",
    "CURRENT_ETOR": 1777878060000,
    "OUTAGE_START": 1777832578000,
    "EST_CUSTOMERS": 13,
    "OUTAGE_CAUSE": "EMERG REPAIRS",
    "CREW_CURRENT_STATUS": "Crew On Site",
    "LAST_UPDATE": 1777847043000,
    "OUTAGE_START_TEXT": "2026-05-03T18:22:58Z",
    "LAST_UPDATE_TEXT": "2026-05-03T22:24:03Z",
    "CURRENT_ETOR_TEXT": "2026-05-04T07:01:00Z"
   },
   "geometry": {
    "x": -13584226.933899999,
    "y": 4481146.4145999998
   }
  },
  {
   "attributes": {
    "OUTAGE_ID": "239055",
    "CURRENT_ETOR": 1777870800000,
    "OUTAGE_START": 1777836032000,
    "EST_CUSTOMERS": 4,
    "OUTAGE_CAUSE": "EMERG REPAIRS",
    "CREW_CURRENT_STATUS": "Crew Enroute",
    "LAST_UPDATE": 1777856181000,
    "OUTAGE_START_TEXT": "2026-05-03T19:20:32Z",
    "LAST_UPDATE_TEXT": "2026-05-04T00:56:21Z",
    "CURRENT_ETOR_TEXT": "2026-05-04T05:00:00Z"
   },
   "geometry": {
    "x": -13565363.1424,
    "y": 4381195.568599999
   }
  },
  {
   "attributes": {
    "OUTAGE_ID": "239119",
    "CURRENT_ETOR": 1777885200000,
    "OUTAGE_START": 1777847772000,
    "EST_CUSTOMERS": 12,
    "OUTAGE_CAUSE": "REPAIR WIRE DWN",
    "CREW_CURRENT_STATUS": "Awaiting Crew",
    "LAST_UPDATE": 1777858309000,
    "OUTAGE_START_TEXT": "2026-05-03T22:36:12Z",
    "LAST_UPDATE_TEXT": "2026-05-04T01:31:49Z",
    "CURRENT_ETOR_TEXT": "2026-05-04T09:00:00Z"
   },
   "geometry": {
    "x": -13479046.701299999,
    "y": 4865825.5307999998
   }
  },
  {
   "attributes": {
    "OUTAGE_ID": "239131",
    "CURRENT_ETOR": 1777881600000,
    "OUTAGE_START": 1777850378000,
    "EST_CUSTOMERS": 2,
    "OUTAGE_CAUSE": "EMERG REPAIRS",
    "CREW_CURRENT_STATUS": "Awaiting Crew",
    "LAST_UPDATE": 1777854763000,
    "OUTAGE_START_TEXT": "2026-05-03T23:19:38Z",
    "LAST_UPDATE_TEXT": "2026-05-04T00:32:43Z",
    "CURRENT_ETOR_TEXT": "2026-05-04T08:00:00Z"
   },
   "geometry": {
    "x": -13693814.2412,
    "y": 4645574.1032999977
   }
  },
  {
   "attributes": {
    "OUTAGE_ID": "239186",
    "CURRENT_ETOR": 1777869000000,
    "OUTAGE_START": 1777855006000,
    "EST_CUSTOMERS": 1,
    "OUTAGE_CAUSE": null,
    "CREW_CURRENT_STATUS": "Awaiting T-Man",
    "LAST_UPDATE": 1777855015000,
    "OUTAGE_START_TEXT": "2026-05-04T00:36:46Z",
    "LAST_UPDATE_TEXT": "2026-05-04T00:36:55Z",
    "CURRENT_ETOR_TEXT": "2026-05-04T04:30:00Z"
   },
   "geometry": {
    "x": -13677540.2282,
    "y": 4645356.7009000033
   }
  },
  {
   "attributes": {
    "OUTAGE_ID": "239210",
    "CURRENT_ETOR": 1777887900000,
    "OUTAGE_START": 1777861099000,
    "EST_CUSTOMERS": 1,
    "OUTAGE_CAUSE": null,
    "CREW_CURRENT_STATUS": "T-Man Enroute",
    "LAST_UPDATE": 1777861103000,
    "OUTAGE_START_TEXT": "2026-05-04T02:18:19Z",
    "LAST_UPDATE_TEXT": "2026-05-04T02:18:23Z",
    "CURRENT_ETOR_TEXT": "2026-05-04T09:45:00Z"
   },
   "geometry": {
    "x": -13309870.7885,
    "y": 4398973.0398000032
   }
  },
  {
   "attributes": {
    "OUTAGE_ID": "239221",
    "CURRENT_ETOR": 1777885200000,
    "OUTAGE_START": 1777861961000,
    "EST_CUSTOMERS": 116,
    "OUTAGE_CAUSE": "EMERG REPAIRS",
    "CREW_CURRENT_STATUS": "Awaiting T-Man",
    "LAST_UPDATE": 1777862846000,
    "OUTAGE_START_TEXT": "2026-05-04T02:32:41Z",
    "LAST_UPDATE_TEXT": "2026-05-04T02:47:26Z",
    "CURRENT_ETOR_TEXT": "2026-05-04T09:00:00Z"
   },
   "geometry": {
    "x": -13600755.2369,
    "y": 4543394.2761000022
   }
  },
  {
   "attributes": {
    "OUTAGE_ID": "239222",
    "CURRENT_ETOR": 1777887000000,
    "OUTAGE_START": 1777861990000,
    "EST_CUSTOMERS": 1,
    "OUTAGE_CAUSE": "PATROLLING",
    "CREW_CURRENT_STATUS": "T-Man On Site",
    "LAST_UPDATE": 1777862852000,
    "OUTAGE_START_TEXT": "2026-05-04T02:33:10Z",
    "LAST_UPDATE_TEXT": "2026-05-04T02:47:32Z",
    "CURRENT_ETOR_TEXT": "2026-05-04T09:30:00Z"
   },
   "geometry": {
    "x": -13523543.7564,
    "y": 5020921.8949000016
   }
  },
  {
   "attributes": {
    "OUTAGE_ID": "239224",
    "CURRENT_ETOR": null,
    "OUTAGE_START": 1777862242000,
    "EST_CUSTOMERS": 6,
    "OUTAGE_CAUSE": null,
    "CREW_CURRENT_STATUS": "Awaiting T-Man",
    "LAST_UPDATE": 1777862245000,
    "OUTAGE_START_TEXT": "2026-05-04T02:37:22Z",
    "LAST_UPDATE_TEXT": "2026-05-04T02:37:25Z",
    "CURRENT_ETOR_TEXT": null
   },
   "geometry": {
    "x": -13601707.036699999,
    "y": 4544064.2767999992
   }
  }
 ]
}